{"any":{"top1000":[{"id":"daMZa7","owner":{"id":"AG4X6","display_name":"EUNICE"},"value":11773,"didBreak":false},{"id":"5GeN6d","owner":{"id":"AWwNk","display_name":"iwantmore29"},"value":11803,"didBreak":true},{"id":"B1r0rN","owner":{"id":"VJ5OW","display_name":"BaconPancakes"},"value":12367,"didBreak":false},{"id":"Y3lR01","owner":{"id":"VeRvv","display_name":"I never finish anyth"},"value":12464,"didBreak":false},{"id":"1WgO9a","owner":{"id":"bd3zw","display_name":"olivapaa"},"value":12596,"didBreak":false},{"id":"W4oExZ","owner":{"id":"klz3a","display_name":"Heater"},"value":14069,"didBreak":false},{"id":"v8pGOL","owner":{"id":"nR1RO","display_name":"Soba"},"value":14586,"didBreak":false},{"id":"Pew77Y","owner":{"id":"AMjo2","display_name":"Atomguy"},"value":14688,"didBreak":false},{"id":"RM79Nr","owner":{"id":"AaoBM","display_name":"Linuxx\ue066"},"value":15143,"didBreak":false},{"id":"daXvlB","owner":{"id":"b8xPR","display_name":"Herneerius"},"value":16424,"didBreak":false},{"id":"ezyJx9","owner":{"id":"b1zzK","display_name":"Trygeve"},"value":16712,"didBreak":false},{"id":"QmoeEe","owner":{"id":"ArwmL","display_name":"Freedom_IT"},"value":17300,"didBreak":false},{"id":"M5lR12","owner":{"id":"33Gg4","display_name":"Sandor Of The MIsts"},"value":18949,"didBreak":false},{"id":"v8J6Kp","owner":{"id":"JDMOK","display_name":"tokki10"},"value":19147,"didBreak":false},{"id":"LaeJ34","owner":{"id":"xNw8O","display_name":"adambrianschmidt"},"value":19174,"didBreak":true},{"id":"Y3lrMQ","owner":{"id":"nXez7","display_name":"SAM45!!!"},"value":19371,"didBreak":true},{"id":"yl54Pa","owner":{"id":"q7MpJ","display_name":"Scarecrow"},"value":19782,"didBreak":false},{"id":"1W7BBX","owner":{"id":"LmzoD","display_name":"seutimsyab"},"value":20974,"didBreak":false},{"id":"EODQOy","owner":{"id":"mwoE9","display_name":"Mikie"},"value":21178,"didBreak":false},{"id":"XZvlmD","owner":{"id":"b8Z7l","display_name":"Fiku121"},"value":21306,"didBreak":false},{"id":"3W6ZQB","owner":{"id":"AoRgv","display_name":"hmx0311"},"value":21370,"didBreak":false},{"id":"wMQ2K5","owner":{"id":"nLqJ9","display_name":"Kirby Kidd"},"value":21623,"didBreak":false},{"id":"W4Elae","owner":{"id":"V6w9Z","display_name":"Draradech"},"value":24229,"didBreak":false},{"id":"JGyxLx","owner":{"id":"VwE1x","display_name":"Elemental Corgi"},"value":24542,"didBreak":false},{"id":"pQzB89","owner":{"id":"VeqyJ","display_name":"Dregu"},"value":24659,"didBreak":false},{"id":"M5lP0M","owner":{"id":"vMWGp","display_name":"craftingtacos"},"value":24999,"didBreak":false},{"id":"GDpm9g","owner":{"id":"yXBGa","display_name":"wumengyundf"},"value":25019,"didBreak":false},{"id":"mK2q22","owner":{"id":"Vw5QR","display_name":"marciochb"},"value":25078,"didBreak":false},{"id":"l5W0z3","owner":{"id":"Ag9yv","display_name":"DuuSuu"},"value":25292,"didBreak":false},{"id":"qYjvlJ","owner":{"id":"bjk4J","display_name":"duvald16"},"value":25308,"didBreak":false},{"id":"GDlJKo","owner":{"id":"b7xR1","display_name":"QuantiumIm"},"value":25332,"didBreak":false},{"id":"zJjKOW","owner":{"id":"nRJR7","display_name":"Mizuhana"},"value":25332,"didBreak":false},{"id":"451NDK","owner":{"id":"rlD0P","display_name":"Jacowboy"},"value":25760,"didBreak":false},{"id":"DDO5e9","owner":{"id":"VJk8J","display_name":"TTV\/fingeon27"},"value":26430,"didBreak":false},{"id":"l55oeP","owner":{"id":"Ap15m","display_name":"Looming"},"value":26474,"didBreak":false},{"id":"OpKXwK","owner":{"id":"A5lL4","display_name":"Geert wilders"},"value":26916,"didBreak":false},{"id":"6BB32N","owner":{"id":"nQML4","display_name":"Honn"},"value":27298,"didBreak":false},{"id":"jeNDzm","owner":{"id":"RRdNe","display_name":"ShrexyBeast"},"value":27638,"didBreak":true},{"id":"1WWJ7P","owner":{"id":"nK209","display_name":"ellisk1"},"value":27944,"didBreak":false},{"id":"RMarye","owner":{"id":"yX9za","display_name":"Kuato"},"value":28138,"didBreak":false},{"id":"Qm8o34","owner":{"id":"ArkGJ","display_name":"veggie stix"},"value":28341,"didBreak":false},{"id":"XZdKO1","owner":{"id":"VJ5zK","display_name":"jonaTHOT"},"value":28607,"didBreak":false},{"id":"oqMNw3","owner":{"id":"nLdwR","display_name":"chrisrothenhoefer"},"value":28692,"didBreak":false},{"id":"l5MGeP","owner":{"id":"bjBQD","display_name":"\u041c\u0430\u0442\u0447\u0435\u043d\u043e\u0432\u043e\u0432\u0441\u043a\u0438\u0439"},"value":28722,"didBreak":false},{"id":"OpK03R","owner":{"id":"yXwor","display_name":"Man Mage"},"value":28912,"didBreak":false},{"id":"mKJXzX","owner":{"id":"JDda4","display_name":"0123"},"value":28976,"didBreak":false},{"id":"pQJ8m9","owner":{"id":"A59w7","display_name":"aBacIdEe"},"value":29372,"didBreak":true},{"id":"Y3G7Ea","owner":{"id":"bOgdW","display_name":"liquor snurf"},"value":30511,"didBreak":false},{"id":"Y3G8oa","owner":{"id":"bqG1P","display_name":"Jujublackmagic"},"value":30663,"didBreak":false},{"id":"NdMWez","owner":{"id":"AGR7w","display_name":"Bubi"},"value":30817,"didBreak":false},{"id":"EOKDDy","owner":{"id":"Y44Pl","display_name":"Realyum"},"value":31151,"didBreak":false},{"id":"RRqm3x","owner":{"id":"bdlWR","display_name":"popcorniosaurus"},"value":31550,"didBreak":true},{"id":"7lB3Ox","owner":{"id":"bODlX","display_name":"HappyPiggy"},"value":31616,"didBreak":false},{"id":"XZqvNz","owner":{"id":"VlPW4","display_name":"Stabhole"},"value":32017,"didBreak":false},{"id":"daN2MK","owner":{"id":"AEgKy","display_name":"Slutmuffin"},"value":32189,"didBreak":false},{"id":"5GdXNd","owner":{"id":"AWR3R","display_name":"waxton"},"value":32285,"didBreak":false},{"id":"3WQ8MR","owner":{"id":"mwkY4","display_name":"PeterHoHK"},"value":32596,"didBreak":false},{"id":"M5veXr","owner":{"id":"e3yez","display_name":"Krazy Koi Fish"},"value":32607,"didBreak":false},{"id":"PeM6JR","owner":{"id":"bNL9G","display_name":"crocka123"},"value":32648,"didBreak":false},{"id":"9ZX4rx","owner":{"id":"5QLzZ","display_name":"arvin900"},"value":32692,"didBreak":false},{"id":"jeEOzQ","owner":{"id":"bj0x5","display_name":"Danielos"},"value":33028,"didBreak":false},{"id":"qYZrjJ","owner":{"id":"nyyzN","display_name":"jeremywinick"},"value":33033,"didBreak":false},{"id":"grWlQp","owner":{"id":"q72do","display_name":"True SmolSir"},"value":33126,"didBreak":false},{"id":"KvQ4M9","owner":{"id":"Aowaq","display_name":"Thoomor"},"value":33155,"didBreak":false},{"id":"5G6KK5","owner":{"id":"Z32my","display_name":"jackrunchy"},"value":33528,"didBreak":false},{"id":"6Brr6j","owner":{"id":"AWr3l","display_name":"ya sure"},"value":35205,"didBreak":false},{"id":"5GY7Q4","owner":{"id":"V6wmJ","display_name":"Fabi\u2b50\ufe0fCst"},"value":36312,"didBreak":false},{"id":"RM1ogO","owner":{"id":"nZBPe","display_name":"HiCanIKillYou"},"value":36452,"didBreak":false},{"id":"1Wp6Xj","owner":{"id":"p269o","display_name":"david.c.hagglund"},"value":36887,"didBreak":false},{"id":"pQyE01","owner":{"id":"bd9Nq","display_name":"Herr Zer\u00d8"},"value":37657,"didBreak":false},{"id":"ezJD1m","owner":{"id":"2Wx6z","display_name":"King Dyllan"},"value":38261,"didBreak":false},{"id":"rd6lvP","owner":{"id":"JDKZ5","display_name":"gold torizo"},"value":38427,"didBreak":false},{"id":"a5j7dM","owner":{"id":"gXN5E","display_name":"CasualSanta"},"value":38580,"didBreak":false},{"id":"M5L0Pv","owner":{"id":"VJBp4","display_name":"Quantum Nut"},"value":38644,"didBreak":false},{"id":"wMNEvz","owner":{"id":"bdlZ4","display_name":"CkyNik"},"value":38810,"didBreak":false},{"id":"grM83J","owner":{"id":"AMk3N","display_name":"lionale29ten"},"value":39240,"didBreak":false},{"id":"grMqwJ","owner":{"id":"7R4eR","display_name":"grande pr\u00e9cipitation du moment"},"value":39342,"didBreak":false},{"id":"KvxJd7","owner":{"id":"bqgNJ","display_name":"French"},"value":39664,"didBreak":false},{"id":"5G6dpp","owner":{"id":"AMrq9","display_name":"Jormungandr"},"value":39785,"didBreak":false},{"id":"a5qoql","owner":{"id":"b8qPL","display_name":"bobthebike"},"value":39853,"didBreak":false},{"id":"wMBOQ2","owner":{"id":"VJMRJ","display_name":"forgiven__"},"value":39891,"didBreak":false},{"id":"1WzdP5","owner":{"id":"q73ge","display_name":"Friar Laurence"},"value":39901,"didBreak":false},{"id":"gry9Ee","owner":{"id":"b1EWK","display_name":"lukas.bornheim"},"value":39904,"didBreak":false},{"id":"6BlaBo","owner":{"id":"n9jRJ","display_name":"\u2468Beloved Tomboyish Girl\u2468"},"value":40203,"didBreak":false},{"id":"5GeB1J","owner":{"id":"bqw0J","display_name":"b00urnz"},"value":40653,"didBreak":false},{"id":"Ndjp1G","owner":{"id":"RRmE2","display_name":"piccolo_SPA"},"value":40925,"didBreak":false},{"id":"pQyGJ1","owner":{"id":"b3Gq3","display_name":"colinblue57"},"value":41316,"didBreak":false},{"id":"8zzw2L","owner":{"id":"Arrk3","display_name":"davidloh"},"value":41474,"didBreak":false},{"id":"Qml3Jv","owner":{"id":"VPNJY","display_name":"m4w30"},"value":41700,"didBreak":false},{"id":"5GPzGx","owner":{"id":"b1vyY","display_name":"zezetel"},"value":41796,"didBreak":false},{"id":"RMN8v2","owner":{"id":"b8EaP","display_name":"Peppsy"},"value":41833,"didBreak":false},{"id":"0ZKqW1","owner":{"id":"nZN82","display_name":"\u263c \u263c \u263c"},"value":42885,"didBreak":false},{"id":"RMmW0j","owner":{"id":"b3NwR","display_name":"hopstalgic"},"value":43058,"didBreak":false},{"id":"7lW0qR","owner":{"id":"bxO05","display_name":"xBrowi"},"value":43328,"didBreak":false},{"id":"pQRjOZ","owner":{"id":"bm9Pm","display_name":"SmileyFace799"},"value":43608,"didBreak":false},{"id":"k29dk4","owner":{"id":"RRxB8","display_name":"BeljihnWahfl"},"value":43999,"didBreak":false},{"id":"Larzyw","owner":{"id":"bx0jx","display_name":"CasterNinja"},"value":44144,"didBreak":false},{"id":"DDYk82","owner":{"id":"bx1Y7","display_name":"Sloth"},"value":44627,"didBreak":false},{"id":"PewrZX","owner":{"id":"bO2EB","display_name":"getShooked"},"value":44661,"didBreak":false},{"id":"0ZORKj","owner":{"id":"bjkoJ","display_name":"beesman93"},"value":44766,"didBreak":false},{"id":"DDyDxx","owner":{"id":"nXBXz","display_name":"lazy comet"},"value":44891,"didBreak":false},{"id":"9ZWKY4","owner":{"id":"AGwPo","display_name":"FrankNirvana"},"value":44901,"didBreak":false},{"id":"PelwPQ","owner":{"id":"AaKBO","display_name":"BronBerry"},"value":44977,"didBreak":false},{"id":"a5jYWl","owner":{"id":"mwxYW","display_name":"Maruka"},"value":45123,"didBreak":false},{"id":"DDD5z9","owner":{"id":"VJ4X7","display_name":"minecat"},"value":45130,"didBreak":false},{"id":"6BJgDD","owner":{"id":"K8eN0","display_name":"-1-1-"},"value":45459,"didBreak":false},{"id":"5GdQOd","owner":{"id":"b7oO6","display_name":"Rico The Saboteur"},"value":45583,"didBreak":false},{"id":"RMO0R8","owner":{"id":"Pg2Dk","display_name":"Craze"},"value":45591,"didBreak":false},{"id":"je6rJR","owner":{"id":"nZqEl","display_name":"thueman"},"value":45922,"didBreak":false},{"id":"B188kN","owner":{"id":"a7N6a","display_name":"Bem"},"value":46045,"didBreak":false},{"id":"455GjK","owner":{"id":"nyMj3","display_name":"Hazmat"},"value":46085,"didBreak":false},{"id":"x3Edw8","owner":{"id":"Pgkdl","display_name":"Arak'nae"},"value":46131,"didBreak":false},{"id":"9Z5Ewk","owner":{"id":"nRXEj","display_name":"Reto"},"value":46200,"didBreak":false},{"id":"GD8Wgg","owner":{"id":"nZ5Ke","display_name":"mbutton15"},"value":46584,"didBreak":false},{"id":"GDXwdD","owner":{"id":"bNk2G","display_name":"Wickerznn \u26ab\u20e4"},"value":46740,"didBreak":false},{"id":"RM19aO","owner":{"id":"bDw4x","display_name":"Jamie"},"value":46969,"didBreak":false},{"id":"45Zdpl","owner":{"id":"nZQrd","display_name":"plush"},"value":47131,"didBreak":false},{"id":"jeN2xR","owner":{"id":"o2zOp","display_name":"ZanyZando"},"value":47182,"didBreak":false},{"id":"M5y4E9","owner":{"id":"A5JLg","display_name":"gijshomminga7"},"value":47314,"didBreak":false},{"id":"zJ2R7k","owner":{"id":"K81qp","display_name":"TucLTU"},"value":47469,"didBreak":false},{"id":"QmM8RL","owner":{"id":"nyJ4N","display_name":"coolninjaboyudude1234"},"value":47533,"didBreak":false},{"id":"a5qBJ3","owner":{"id":"4Lx4l","display_name":"eriks5955"},"value":47979,"didBreak":false},{"id":"JGvwkJ","owner":{"id":"ApW7Z","display_name":"M47145dg"},"value":48053,"didBreak":false},{"id":"B188yK","owner":{"id":"Apl69","display_name":"Donald5790"},"value":48119,"didBreak":false},{"id":"grWeWp","owner":{"id":"JDkWD","display_name":"Hentoad1"},"value":48162,"didBreak":false},{"id":"NdpW3N","owner":{"id":"Avqy4","display_name":"TojaKarol"},"value":48197,"didBreak":false},{"id":"JGymd7","owner":{"id":"ly9wR","display_name":"malizma333"},"value":48431,"didBreak":false},{"id":"M539dN","owner":{"id":"b1D1K","display_name":"BROTHER"},"value":48917,"didBreak":false},{"id":"ylMzXy","owner":{"id":"AgJOv","display_name":"uj030221-3551"},"value":49374,"didBreak":false},{"id":"rdQ16P","owner":{"id":"VPmjR","display_name":"0LL1"},"value":49473,"didBreak":false},{"id":"W4jej4","owner":{"id":"AaJLl","display_name":"palfly15"},"value":49812,"didBreak":false},{"id":"mKQ9kP","owner":{"id":"bqWeX","display_name":"."},"value":49857,"didBreak":false},{"id":"GDoyd9","owner":{"id":"9dW8x","display_name":"frotnight funy"},"value":50018,"didBreak":false},{"id":"Y3QNYQ","owner":{"id":"nRgg7","display_name":"XxTrollFacexX"},"value":50326,"didBreak":false},{"id":"M5l4N2","owner":{"id":"nQPB6","display_name":"LankyBoi"},"value":50373,"didBreak":false},{"id":"B1Qv97","owner":{"id":"AaoeX","display_name":"MageGeraint"},"value":50457,"didBreak":false},{"id":"3W47gB","owner":{"id":"nKBoL","display_name":"Murkaeus"},"value":50639,"didBreak":false},{"id":"oqqO3q","owner":{"id":"AWRGk","display_name":"\u6ed1\u5730\u4e0a\u4e4b\u5c0f\u7a3d"},"value":50753,"didBreak":false},{"id":"l52okL","owner":{"id":"VYB2y","display_name":"dylanwenger9"},"value":50803,"didBreak":false},{"id":"pQyMl8","owner":{"id":"AaqKe","display_name":"Pugloney29"},"value":50939,"didBreak":false},{"id":"ezMxWM","owner":{"id":"bmeEG","display_name":"Orbifold"},"value":51026,"didBreak":false},{"id":"GDoGRg","owner":{"id":"VwGgy","display_name":"cam"},"value":51101,"didBreak":false},{"id":"7lgwY7","owner":{"id":"Z3W4d","display_name":"zhaohuaye54"},"value":51103,"didBreak":false},{"id":"9ZQ27r","owner":{"id":"Y4mQ9","display_name":"Bram2323"},"value":51266,"didBreak":false},{"id":"8zG0G5","owner":{"id":"AvZPD","display_name":"Teh"},"value":51266,"didBreak":false},{"id":"6BBzlq","owner":{"id":"AWO1z","display_name":"Mr.ThisGuy"},"value":51579,"didBreak":false},{"id":"qY6D6P","owner":{"id":"b2Y9a","display_name":"Terra_Pringles"},"value":51846,"didBreak":false},{"id":"a5oKYa","owner":{"id":"bjrkJ","display_name":"gashpot"},"value":52022,"didBreak":false},{"id":"v8jlEy","owner":{"id":"xN3pP","display_name":"loganstephensmith"},"value":52211,"didBreak":false},{"id":"ylg0P3","owner":{"id":"33Qy4","display_name":"Cg089"},"value":52461,"didBreak":false},{"id":"QmvrZG","owner":{"id":"bqRNq","display_name":"Qthey"},"value":52484,"didBreak":false},{"id":"PeKJow","owner":{"id":"4LX0l","display_name":"Supernye"},"value":52530,"didBreak":false},{"id":"3WYNx9","owner":{"id":"dj944","display_name":"lee731017"},"value":52544,"didBreak":false},{"id":"daMNLB","owner":{"id":"VeN45","display_name":"Jeevus"},"value":52784,"didBreak":false},{"id":"qYMmpM","owner":{"id":"nRz77","display_name":"snowmaniac"},"value":53126,"didBreak":false},{"id":"l5zW37","owner":{"id":"p2MBw","display_name":"Jakke"},"value":53483,"didBreak":false},{"id":"6B8y3N","owner":{"id":"vMpo9","display_name":"Maistas"},"value":53695,"didBreak":false},{"id":"mKWdW9","owner":{"id":"bdXz7","display_name":"Aya"},"value":53782,"didBreak":false},{"id":"RM1rJ7","owner":{"id":"VPrKw","display_name":"nhaven14"},"value":53885,"didBreak":false},{"id":"PeKZmY","owner":{"id":"nRDjx","display_name":"HowieFTW"},"value":54291,"didBreak":false},{"id":"mKEZjW","owner":{"id":"q7dyW","display_name":"adamladam484"},"value":54381,"didBreak":false},{"id":"RM1Bg9","owner":{"id":"q7e4o","display_name":"Uniquepotatoes"},"value":54728,"didBreak":false},{"id":"RM7BoQ","owner":{"id":"bmW4E","display_name":"pome.\ud83d\ude08"},"value":54932,"didBreak":false},{"id":"5GGdo5","owner":{"id":"nKxxm","display_name":"Pengujedi"},"value":55107,"didBreak":false},{"id":"pQ9E12","owner":{"id":"bmvMP","display_name":"Shadow Blades"},"value":55107,"didBreak":false},{"id":"a5DE3l","owner":{"id":"JDQaJ","display_name":"spanner"},"value":55111,"didBreak":false},{"id":"ZLrJDl","owner":{"id":"p2v1o","display_name":"marcus.wasastjerna"},"value":55153,"didBreak":false},{"id":"45OLqM","owner":{"id":"nXM0Q","display_name":"hakejb1"},"value":55154,"didBreak":false},{"id":"0ZK20o","owner":{"id":"nR618","display_name":"Kn1GhT05"},"value":55208,"didBreak":false},{"id":"Op8adm","owner":{"id":"b8vqP","display_name":"Dragon Fruit"},"value":55219,"didBreak":false},{"id":"wMNJjm","owner":{"id":"Arv0Q","display_name":"Navet"},"value":55381,"didBreak":false},{"id":"l5ErMg","owner":{"id":"VJ32m","display_name":"rco915"},"value":55411,"didBreak":false},{"id":"EOaLRy","owner":{"id":"ABr6N","display_name":"Thudios"},"value":55556,"didBreak":false},{"id":"Ndg4JD","owner":{"id":"nR4vy","display_name":"Beefshankz"},"value":55815,"didBreak":false},{"id":"gr9pxE","owner":{"id":"bODpX","display_name":"Groovemouse"},"value":55839,"didBreak":false},{"id":"zJdRQ3","owner":{"id":"V6QoJ","display_name":"tomka700"},"value":55908,"didBreak":false},{"id":"l5rLB3","owner":{"id":"bdPo4","display_name":"smokedscrod"},"value":56118,"didBreak":false},{"id":"EOed6R","owner":{"id":"nQ4Rv","display_name":"razpe"},"value":56123,"didBreak":false},{"id":"RMvP7x","owner":{"id":"2WZgZ","display_name":"Katamari (old)"},"value":56372,"didBreak":false},{"id":"XZoYqa","owner":{"id":"AEeGD","display_name":"Slim"},"value":56526,"didBreak":false},{"id":"OpdqBm","owner":{"id":"A0Gze","display_name":"Bot Zket"},"value":56772,"didBreak":false},{"id":"l5NZvE","owner":{"id":"bdXQq","display_name":"Starstorm"},"value":56815,"didBreak":false},{"id":"v8jWxa","owner":{"id":"VYMJR","display_name":"dtee3"},"value":56955,"didBreak":false},{"id":"6B8EjD","owner":{"id":"VeRrM","display_name":"Chuek"},"value":56979,"didBreak":false},{"id":"Y3Qwgy","owner":{"id":"nR1NQ","display_name":"Valnix"},"value":56988,"didBreak":false},{"id":"k2oo3r","owner":{"id":"AgkRJ","display_name":"Miner_vdv"},"value":56988,"didBreak":false},{"id":"XZBKGz","owner":{"id":"XLo7Z","display_name":"TheRainCrow"},"value":57060,"didBreak":false},{"id":"45Z7GZ","owner":{"id":"AgBMK","display_name":"YottaCat"},"value":57179,"didBreak":false},{"id":"oqJ2Rj","owner":{"id":"bmYlr","display_name":"Catraption"},"value":57181,"didBreak":false},{"id":"W4Eqg4","owner":{"id":"A5jgd","display_name":"castigo"},"value":57237,"didBreak":false},{"id":"B1Q9g9","owner":{"id":"bxOWx","display_name":"SwordlessMimeTown"},"value":57412,"didBreak":false},{"id":"PewlEY","owner":{"id":"VeoE9","display_name":"E."},"value":57423,"didBreak":false},{"id":"M5yOPD","owner":{"id":"zodKM","display_name":"Moochywa"},"value":57483,"didBreak":false},{"id":"0ZE38r","owner":{"id":"jM3P5","display_name":"bille"},"value":57505,"didBreak":false},{"id":"LaED86","owner":{"id":"AG0zm","display_name":"315Lukas"},"value":57619,"didBreak":false},{"id":"3W5JYB","owner":{"id":"AGkwR","display_name":"theo.louesdon"},"value":57881,"didBreak":false},{"id":"2Zq1MZ","owner":{"id":"Aawpa","display_name":"geroniberry"},"value":58007,"didBreak":true},{"id":"mKQZom","owner":{"id":"bxEPx","display_name":"Azean"},"value":58023,"didBreak":false},{"id":"8zQadl","owner":{"id":"ABwl7","display_name":"Aklhys"},"value":58316,"didBreak":false},{"id":"ZLQY79","owner":{"id":"bOoQB","display_name":"Bushy"},"value":58353,"didBreak":true},{"id":"DDLWp4","owner":{"id":"V6wN9","display_name":"rafaelcr44"},"value":58382,"didBreak":false},{"id":"XZdJg7","owner":{"id":"xNJv8","display_name":"Gibby"},"value":58443,"didBreak":false},{"id":"8zBq3m","owner":{"id":"A0P71","display_name":"Lord_F8L"},"value":58532,"didBreak":false},{"id":"oqD4dp","owner":{"id":"ABPyz","display_name":"_MooseCheese_"},"value":58597,"didBreak":false},{"id":"GDpRPD","owner":{"id":"RRe38","display_name":"Lorz"},"value":58747,"didBreak":false},{"id":"XZXoPe","owner":{"id":"A59D5","display_name":"KingIceCream"},"value":58856,"didBreak":false},{"id":"RMO29r","owner":{"id":"VeJB1","display_name":"Volardin"},"value":58880,"didBreak":false},{"id":"rdJZYX","owner":{"id":"vMze9","display_name":"Enredar1457"},"value":59005,"didBreak":false},{"id":"v8kGyP","owner":{"id":"o2ERX","display_name":"Waity5"},"value":59036,"didBreak":false},{"id":"ylQ038","owner":{"id":"AaKZB","display_name":"Zoom"},"value":59154,"didBreak":false},{"id":"Y3mQwl","owner":{"id":"Vl89p","display_name":"Kronos"},"value":59155,"didBreak":false},{"id":"ZLQd1X","owner":{"id":"bd997","display_name":"Marijn"},"value":59185,"didBreak":false},{"id":"KvQrom","owner":{"id":"VzMq3","display_name":"WiadrOrbaiW"},"value":59244,"didBreak":false},{"id":"k2zOyp","owner":{"id":"b72RP","display_name":"Smplstx"},"value":59320,"didBreak":false},{"id":"5GL2w4","owner":{"id":"A54WO","display_name":"Platypus"},"value":59340,"didBreak":false},{"id":"7lxpg1","owner":{"id":"nRQXy","display_name":"zerd"},"value":59382,"didBreak":false},{"id":"pQjo5w","owner":{"id":"Vzx1Y","display_name":"Doggo"},"value":59402,"didBreak":false},{"id":"pQ1zp8","owner":{"id":"bO8Xm","display_name":"endy80"},"value":59406,"didBreak":false},{"id":"La306z","owner":{"id":"N5vwK","display_name":"ancovd12"},"value":59413,"didBreak":false},{"id":"3W12oO","owner":{"id":"b7N6z","display_name":"superneuras"},"value":59461,"didBreak":false},{"id":"zJg64M","owner":{"id":"nRawr","display_name":"AkillezII"},"value":59507,"didBreak":false},{"id":"pQQGN1","owner":{"id":"W7ZMe","display_name":"rainy"},"value":59587,"didBreak":false},{"id":"pQW8ed","owner":{"id":"gXXXO","display_name":"\u272a tom1911"},"value":59612,"didBreak":false},{"id":"qY6m34","owner":{"id":"vMlrD","display_name":"cornshitfuck"},"value":59665,"didBreak":false},{"id":"Kvvmkk","owner":{"id":"AaDNX","display_name":"Go Seigen"},"value":59761,"didBreak":false},{"id":"45xaG6","owner":{"id":"AGRgD","display_name":"Bull Moose"},"value":59767,"didBreak":true},{"id":"rd92rJ","owner":{"id":"b8Jkl","display_name":"Sloane"},"value":59787,"didBreak":false},{"id":"Pepqal","owner":{"id":"Vz87D","display_name":"Kastrull"},"value":59792,"didBreak":false},{"id":"wMyGXO","owner":{"id":"bdM2B","display_name":"BorkFanBoy"},"value":59842,"didBreak":false},{"id":"RMOL8e","owner":{"id":"bd2PR","display_name":"gundu_001"},"value":59853,"didBreak":false},{"id":"rdKN4J","owner":{"id":"AogYX","display_name":"Caligula"},"value":59884,"didBreak":false},{"id":"pQ6LXw","owner":{"id":"VlxvR","display_name":"Birnfeld"},"value":59891,"didBreak":false},{"id":"qY60jl","owner":{"id":"zoJYX","display_name":"GolEden"},"value":59948,"didBreak":false},{"id":"grNG7K","owner":{"id":"VzP4D","display_name":"Frits"},"value":60016,"didBreak":false},{"id":"W4O4OO","owner":{"id":"b7BDz","display_name":"Mulalu"},"value":60025,"didBreak":false},{"id":"ezKxMz","owner":{"id":"xNEB5","display_name":"DudeGuy04"},"value":60025,"didBreak":true},{"id":"8zmjL5","owner":{"id":"nR1Je","display_name":"Qcrist"},"value":60048,"didBreak":false},{"id":"l5QjEj","owner":{"id":"b21WG","display_name":"Hyppis"},"value":60050,"didBreak":false},{"id":"v8qw7L","owner":{"id":"VlqWL","display_name":"Skriban"},"value":60089,"didBreak":false},{"id":"45W4MK","owner":{"id":"nRNB2","display_name":"BuildingDR"},"value":60115,"didBreak":false},{"id":"ezRRm9","owner":{"id":"bN7JG","display_name":"AZ-LT"},"value":60156,"didBreak":false},{"id":"Peg35R","owner":{"id":"VY6rQ","display_name":"The Toasted Marshmallow"},"value":60214,"didBreak":false},{"id":"yllGKR","owner":{"id":"VlMk3","display_name":"RisingStar"},"value":60216,"didBreak":false},{"id":"jeJqqm","owner":{"id":"bm59L","display_name":"siDohK"},"value":60251,"didBreak":false},{"id":"Y3Gkxz","owner":{"id":"e37m9","display_name":"Teywer"},"value":60273,"didBreak":false},{"id":"GDR3OD","owner":{"id":"b29Kk","display_name":"pineapplebacon777"},"value":60295,"didBreak":false},{"id":"5G6WPZ","owner":{"id":"b712w","display_name":"schwiftyking"},"value":60312,"didBreak":false},{"id":"7lgedx","owner":{"id":"VJYmJ","display_name":"Typodestoyer"},"value":60314,"didBreak":false},{"id":"l5B1eP","owner":{"id":"QO5yv","display_name":"LUCse MENSEN"},"value":60360,"didBreak":false},{"id":"W4M9Je","owner":{"id":"Aa2El","display_name":"Matty90509"},"value":60368,"didBreak":false},{"id":"RM7KRO","owner":{"id":"nKEG3","display_name":"BOYAR"},"value":60380,"didBreak":false},{"id":"zJdJ9Y","owner":{"id":"Z3Nxl","display_name":"jakers0011"},"value":60388,"didBreak":false},{"id":"2Wy8e3","owner":{"id":"V4yxZ","display_name":"Zautos"},"value":60389,"didBreak":true},{"id":"GDpaDw","owner":{"id":"b1gOK","display_name":"Existence is Pain"},"value":60423,"didBreak":false},{"id":"GD8K89","owner":{"id":"VeJO1","display_name":"\u6e05\u6e05\u82b1\u72f8\u732b"},"value":60446,"didBreak":false},{"id":"l5zg6P","owner":{"id":"7Rzez","display_name":"Loner"},"value":60454,"didBreak":false},{"id":"oqE0d6","owner":{"id":"nLRN9","display_name":"Fockey15"},"value":60484,"didBreak":false},{"id":"9Z7kLx","owner":{"id":"a7Kda","display_name":"Outragedgamer14"},"value":60513,"didBreak":false},{"id":"jeENMp","owner":{"id":"b209D","display_name":"~ Smithy ~"},"value":60513,"didBreak":false},{"id":"ez39dQ","owner":{"id":"Lmd3w","display_name":"Whyit1"},"value":60533,"didBreak":false},{"id":"qYxl6X","owner":{"id":"b7w86","display_name":"vkelloku"},"value":60569,"didBreak":false},{"id":"grNE8e","owner":{"id":"nygK7","display_name":"kristoffer"},"value":60625,"didBreak":false},{"id":"pQRLk2","owner":{"id":"1q0PK","display_name":"joseph.pesqui"},"value":60642,"didBreak":false},{"id":"45aM0M","owner":{"id":"6qr1D","display_name":"Oddysen"},"value":60662,"didBreak":false},{"id":"LagGKR","owner":{"id":"AaXLe","display_name":"jacob.hh"},"value":60686,"didBreak":false},{"id":"0ZEP8w","owner":{"id":"AGp6g","display_name":"SpandexN00dle"},"value":60707,"didBreak":false},{"id":"PeGKyw","owner":{"id":"nXWw7","display_name":"Diggsey"},"value":60746,"didBreak":false},{"id":"GDXrDq","owner":{"id":"nQ6Be","display_name":"I Like Ugly Mammals."},"value":60801,"didBreak":false},{"id":"7lLKlz","owner":{"id":"b8LXR","display_name":"celesteal"},"value":60826,"didBreak":false},{"id":"0ZK9Jj","owner":{"id":"nXd2E","display_name":"Kubu\u015b :*"},"value":60828,"didBreak":false},{"id":"ylQ8W6","owner":{"id":"OBwWJ","display_name":"GeGe"},"value":60831,"didBreak":false},{"id":"2Zq9Zw","owner":{"id":"b3v8L","display_name":"Toto00"},"value":60835,"didBreak":false},{"id":"Qm6jpO","owner":{"id":"N559o","display_name":"7DimensionalParrot"},"value":60858,"didBreak":false},{"id":"Y3E6Zl","owner":{"id":"VPMeX","display_name":"DildoBike"},"value":60869,"didBreak":false},{"id":"LampWa","owner":{"id":"b1QmX","display_name":"chenail.liam"},"value":60898,"didBreak":false},{"id":"k2mXDr","owner":{"id":"VPQRY","display_name":"R"},"value":60903,"didBreak":false},{"id":"2ZzBZJ","owner":{"id":"bNPZo","display_name":"Big Dick Brian"},"value":60911,"didBreak":false},{"id":"oqY9O5","owner":{"id":"nkd9R","display_name":"Oreocraft2"},"value":60938,"didBreak":false},{"id":"LaDloz","owner":{"id":"9dwLJ","display_name":"Kalorienreduziert"},"value":60954,"didBreak":false},{"id":"v8XDQ1","owner":{"id":"b2Q0w","display_name":"Luna Kampling"},"value":60956,"didBreak":false},{"id":"XZov6D","owner":{"id":"Ag9ae","display_name":"CoolCorps"},"value":60966,"didBreak":false},{"id":"7l0241","owner":{"id":"nZ47X","display_name":"Ogremor"},"value":60971,"didBreak":false},{"id":"8zGREa","owner":{"id":"EBzP2","display_name":"lollyH2O"},"value":60994,"didBreak":false},{"id":"QmoeN4","owner":{"id":"Vw7oR","display_name":"Salty Snail"},"value":60997,"didBreak":false},{"id":"B17elR","owner":{"id":"Vzl1G","display_name":"timmyaustin29.as"},"value":60998,"didBreak":false},{"id":"mKWm0r","owner":{"id":"AMxzX","display_name":"bumperdo09"},"value":61000,"didBreak":false},{"id":"jeDYr7","owner":{"id":"a7OjO","display_name":"tetsu_yamamon"},"value":61000,"didBreak":false},{"id":"Qm4qww","owner":{"id":"ABvZ9","display_name":"twistedsister86"},"value":64166,"didBreak":true},{"id":"ezBMvz","owner":{"id":"A0wve","display_name":"Cupar Guy"},"value":71516,"didBreak":false}],"metadata":{"uniqueRanksCount":320}},"unbroken":{"top1000":[{"id":"daMZa7","owner":{"id":"AG4X6","display_name":"EUNICE"},"value":11773,"didBreak":false},{"id":"B1r0rN","owner":{"id":"VJ5OW","display_name":"BaconPancakes"},"value":12367,"didBreak":false},{"id":"Y3lR01","owner":{"id":"VeRvv","display_name":"I never finish anyth"},"value":12464,"didBreak":false},{"id":"1WgO9a","owner":{"id":"bd3zw","display_name":"olivapaa"},"value":12596,"didBreak":false},{"id":"mKgm29","owner":{"id":"AWwNk","display_name":"iwantmore29"},"value":13505,"didBreak":false},{"id":"W4oExZ","owner":{"id":"klz3a","display_name":"Heater"},"value":14069,"didBreak":false},{"id":"v8pGOL","owner":{"id":"nR1RO","display_name":"Soba"},"value":14586,"didBreak":false},{"id":"Pew77Y","owner":{"id":"AMjo2","display_name":"Atomguy"},"value":14688,"didBreak":false},{"id":"RM79Nr","owner":{"id":"AaoBM","display_name":"Linuxx\ue066"},"value":15143,"didBreak":false},{"id":"daXvlB","owner":{"id":"b8xPR","display_name":"Herneerius"},"value":16424,"didBreak":false},{"id":"ezyJx9","owner":{"id":"b1zzK","display_name":"Trygeve"},"value":16712,"didBreak":false},{"id":"QmoeEe","owner":{"id":"ArwmL","display_name":"Freedom_IT"},"value":17300,"didBreak":false},{"id":"M5lR12","owner":{"id":"33Gg4","display_name":"Sandor Of The MIsts"},"value":18949,"didBreak":false},{"id":"v8J6Kp","owner":{"id":"JDMOK","display_name":"tokki10"},"value":19147,"didBreak":false},{"id":"yl54Pa","owner":{"id":"q7MpJ","display_name":"Scarecrow"},"value":19782,"didBreak":false},{"id":"B1LJ39","owner":{"id":"xNw8O","display_name":"adambrianschmidt"},"value":19941,"didBreak":false},{"id":"1W7BBX","owner":{"id":"LmzoD","display_name":"seutimsyab"},"value":20974,"didBreak":false},{"id":"EODQOy","owner":{"id":"mwoE9","display_name":"Mikie"},"value":21178,"didBreak":false},{"id":"XZvlmD","owner":{"id":"b8Z7l","display_name":"Fiku121"},"value":21306,"didBreak":false},{"id":"3W6ZQB","owner":{"id":"AoRgv","display_name":"hmx0311"},"value":21370,"didBreak":false},{"id":"wMQ2K5","owner":{"id":"nLqJ9","display_name":"Kirby Kidd"},"value":21623,"didBreak":false},{"id":"W4Elae","owner":{"id":"V6w9Z","display_name":"Draradech"},"value":24229,"didBreak":false},{"id":"JGyxLx","owner":{"id":"VwE1x","display_name":"Elemental Corgi"},"value":24542,"didBreak":false},{"id":"pQzB89","owner":{"id":"VeqyJ","display_name":"Dregu"},"value":24659,"didBreak":false},{"id":"M5lP0M","owner":{"id":"vMWGp","display_name":"craftingtacos"},"value":24999,"didBreak":false},{"id":"GDpm9g","owner":{"id":"yXBGa","display_name":"wumengyundf"},"value":25019,"didBreak":false},{"id":"mK2q22","owner":{"id":"Vw5QR","display_name":"marciochb"},"value":25078,"didBreak":false},{"id":"l5W0z3","owner":{"id":"Ag9yv","display_name":"DuuSuu"},"value":25292,"didBreak":false},{"id":"qYjvlJ","owner":{"id":"bjk4J","display_name":"duvald16"},"value":25308,"didBreak":false},{"id":"GDlJKo","owner":{"id":"b7xR1","display_name":"QuantiumIm"},"value":25332,"didBreak":false},{"id":"zJjKOW","owner":{"id":"nRJR7","display_name":"Mizuhana"},"value":25332,"didBreak":false},{"id":"451NDK","owner":{"id":"rlD0P","display_name":"Jacowboy"},"value":25760,"didBreak":false},{"id":"DDO5e9","owner":{"id":"VJk8J","display_name":"TTV\/fingeon27"},"value":26430,"didBreak":false},{"id":"l55oeP","owner":{"id":"Ap15m","display_name":"Looming"},"value":26474,"didBreak":false},{"id":"OpKXwK","owner":{"id":"A5lL4","display_name":"Geert wilders"},"value":26916,"didBreak":false},{"id":"6BB32N","owner":{"id":"nQML4","display_name":"Honn"},"value":27298,"didBreak":false},{"id":"1WWJ7P","owner":{"id":"nK209","display_name":"ellisk1"},"value":27944,"didBreak":false},{"id":"W4MjNe","owner":{"id":"RRdNe","display_name":"ShrexyBeast"},"value":27963,"didBreak":false},{"id":"RMarye","owner":{"id":"yX9za","display_name":"Kuato"},"value":28138,"didBreak":false},{"id":"Qm8o34","owner":{"id":"ArkGJ","display_name":"veggie stix"},"value":28341,"didBreak":false},{"id":"XZdKO1","owner":{"id":"VJ5zK","display_name":"jonaTHOT"},"value":28607,"didBreak":false},{"id":"oqMNw3","owner":{"id":"nLdwR","display_name":"chrisrothenhoefer"},"value":28692,"didBreak":false},{"id":"l5MGeP","owner":{"id":"bjBQD","display_name":"\u041c\u0430\u0442\u0447\u0435\u043d\u043e\u0432\u043e\u0432\u0441\u043a\u0438\u0439"},"value":28722,"didBreak":false},{"id":"OpK03R","owner":{"id":"yXwor","display_name":"Man Mage"},"value":28912,"didBreak":false},{"id":"mKJXzX","owner":{"id":"JDda4","display_name":"0123"},"value":28976,"didBreak":false},{"id":"Y3G7Ea","owner":{"id":"bOgdW","display_name":"liquor snurf"},"value":30511,"didBreak":false},{"id":"Y3G8oa","owner":{"id":"bqG1P","display_name":"Jujublackmagic"},"value":30663,"didBreak":false},{"id":"NdMWez","owner":{"id":"AGR7w","display_name":"Bubi"},"value":30817,"didBreak":false},{"id":"EOKDDy","owner":{"id":"Y44Pl","display_name":"Realyum"},"value":31151,"didBreak":false},{"id":"7lB3Ox","owner":{"id":"bODlX","display_name":"HappyPiggy"},"value":31616,"didBreak":false},{"id":"XZqvNz","owner":{"id":"VlPW4","display_name":"Stabhole"},"value":32017,"didBreak":false},{"id":"daN2MK","owner":{"id":"AEgKy","display_name":"Slutmuffin"},"value":32189,"didBreak":false},{"id":"5GdXNd","owner":{"id":"AWR3R","display_name":"waxton"},"value":32285,"didBreak":false},{"id":"3WQ8MR","owner":{"id":"mwkY4","display_name":"PeterHoHK"},"value":32596,"didBreak":false},{"id":"M5veXr","owner":{"id":"e3yez","display_name":"Krazy Koi Fish"},"value":32607,"didBreak":false},{"id":"PeM6JR","owner":{"id":"bNL9G","display_name":"crocka123"},"value":32648,"didBreak":false},{"id":"9ZX4rx","owner":{"id":"5QLzZ","display_name":"arvin900"},"value":32692,"didBreak":false},{"id":"jeEOzQ","owner":{"id":"bj0x5","display_name":"Danielos"},"value":33028,"didBreak":false},{"id":"qYZrjJ","owner":{"id":"nyyzN","display_name":"jeremywinick"},"value":33033,"didBreak":false},{"id":"grWlQp","owner":{"id":"q72do","display_name":"True SmolSir"},"value":33126,"didBreak":false},{"id":"KvQ4M9","owner":{"id":"Aowaq","display_name":"Thoomor"},"value":33155,"didBreak":false},{"id":"5G6KK5","owner":{"id":"Z32my","display_name":"jackrunchy"},"value":33528,"didBreak":false},{"id":"NdBqZz","owner":{"id":"A59w7","display_name":"aBacIdEe"},"value":35159,"didBreak":false},{"id":"6Brr6j","owner":{"id":"AWr3l","display_name":"ya sure"},"value":35205,"didBreak":false},{"id":"5GY7Q4","owner":{"id":"V6wmJ","display_name":"Fabi\u2b50\ufe0fCst"},"value":36312,"didBreak":false},{"id":"RM1ogO","owner":{"id":"nZBPe","display_name":"HiCanIKillYou"},"value":36452,"didBreak":false},{"id":"1Wp6Xj","owner":{"id":"p269o","display_name":"david.c.hagglund"},"value":36887,"didBreak":false},{"id":"pQyE01","owner":{"id":"bd9Nq","display_name":"Herr Zer\u00d8"},"value":37657,"didBreak":false},{"id":"ezJD1m","owner":{"id":"2Wx6z","display_name":"King Dyllan"},"value":38261,"didBreak":false},{"id":"rd6lvP","owner":{"id":"JDKZ5","display_name":"gold torizo"},"value":38427,"didBreak":false},{"id":"a5j7dM","owner":{"id":"gXN5E","display_name":"CasualSanta"},"value":38580,"didBreak":false},{"id":"M5L0Pv","owner":{"id":"VJBp4","display_name":"Quantum Nut"},"value":38644,"didBreak":false},{"id":"wMNEvz","owner":{"id":"bdlZ4","display_name":"CkyNik"},"value":38810,"didBreak":false},{"id":"grM83J","owner":{"id":"AMk3N","display_name":"lionale29ten"},"value":39240,"didBreak":false},{"id":"grMqwJ","owner":{"id":"7R4eR","display_name":"grande pr\u00e9cipitation du moment"},"value":39342,"didBreak":false},{"id":"KvxJd7","owner":{"id":"bqgNJ","display_name":"French"},"value":39664,"didBreak":false},{"id":"5G6dpp","owner":{"id":"AMrq9","display_name":"Jormungandr"},"value":39785,"didBreak":false},{"id":"a5qoql","owner":{"id":"b8qPL","display_name":"bobthebike"},"value":39853,"didBreak":false},{"id":"wMBOQ2","owner":{"id":"VJMRJ","display_name":"forgiven__"},"value":39891,"didBreak":false},{"id":"1WzdP5","owner":{"id":"q73ge","display_name":"Friar Laurence"},"value":39901,"didBreak":false},{"id":"gry9Ee","owner":{"id":"b1EWK","display_name":"lukas.bornheim"},"value":39904,"didBreak":false},{"id":"6BlaBo","owner":{"id":"n9jRJ","display_name":"\u2468Beloved Tomboyish Girl\u2468"},"value":40203,"didBreak":false},{"id":"5GeB1J","owner":{"id":"bqw0J","display_name":"b00urnz"},"value":40653,"didBreak":false},{"id":"Ndjp1G","owner":{"id":"RRmE2","display_name":"piccolo_SPA"},"value":40925,"didBreak":false},{"id":"pQyGJ1","owner":{"id":"b3Gq3","display_name":"colinblue57"},"value":41316,"didBreak":false},{"id":"8zzw2L","owner":{"id":"Arrk3","display_name":"davidloh"},"value":41474,"didBreak":false},{"id":"Qml3Jv","owner":{"id":"VPNJY","display_name":"m4w30"},"value":41700,"didBreak":false},{"id":"5GPzGx","owner":{"id":"b1vyY","display_name":"zezetel"},"value":41796,"didBreak":false},{"id":"RMN8v2","owner":{"id":"b8EaP","display_name":"Peppsy"},"value":41833,"didBreak":false},{"id":"0ZKqW1","owner":{"id":"nZN82","display_name":"\u263c \u263c \u263c"},"value":42885,"didBreak":false},{"id":"RMmW0j","owner":{"id":"b3NwR","display_name":"hopstalgic"},"value":43058,"didBreak":false},{"id":"7lW0qR","owner":{"id":"bxO05","display_name":"xBrowi"},"value":43328,"didBreak":false},{"id":"pQRjOZ","owner":{"id":"bm9Pm","display_name":"SmileyFace799"},"value":43608,"didBreak":false},{"id":"k29dk4","owner":{"id":"RRxB8","display_name":"BeljihnWahfl"},"value":43999,"didBreak":false},{"id":"Larzyw","owner":{"id":"bx0jx","display_name":"CasterNinja"},"value":44144,"didBreak":false},{"id":"DDYk82","owner":{"id":"bx1Y7","display_name":"Sloth"},"value":44627,"didBreak":false},{"id":"PewrZX","owner":{"id":"bO2EB","display_name":"getShooked"},"value":44661,"didBreak":false},{"id":"0ZORKj","owner":{"id":"bjkoJ","display_name":"beesman93"},"value":44766,"didBreak":false},{"id":"DDyDxx","owner":{"id":"nXBXz","display_name":"lazy comet"},"value":44891,"didBreak":false},{"id":"9ZWKY4","owner":{"id":"AGwPo","display_name":"FrankNirvana"},"value":44901,"didBreak":false},{"id":"PelwPQ","owner":{"id":"AaKBO","display_name":"BronBerry"},"value":44977,"didBreak":false},{"id":"a5jYWl","owner":{"id":"mwxYW","display_name":"Maruka"},"value":45123,"didBreak":false},{"id":"DDD5z9","owner":{"id":"VJ4X7","display_name":"minecat"},"value":45130,"didBreak":false},{"id":"6BJgDD","owner":{"id":"K8eN0","display_name":"-1-1-"},"value":45459,"didBreak":false},{"id":"5GdQOd","owner":{"id":"b7oO6","display_name":"Rico The Saboteur"},"value":45583,"didBreak":false},{"id":"RMO0R8","owner":{"id":"Pg2Dk","display_name":"Craze"},"value":45591,"didBreak":false},{"id":"je6rJR","owner":{"id":"nZqEl","display_name":"thueman"},"value":45922,"didBreak":false},{"id":"B188kN","owner":{"id":"a7N6a","display_name":"Bem"},"value":46045,"didBreak":false},{"id":"455GjK","owner":{"id":"nyMj3","display_name":"Hazmat"},"value":46085,"didBreak":false},{"id":"x3Edw8","owner":{"id":"Pgkdl","display_name":"Arak'nae"},"value":46131,"didBreak":false},{"id":"9Z5Ewk","owner":{"id":"nRXEj","display_name":"Reto"},"value":46200,"didBreak":false},{"id":"GD8Wgg","owner":{"id":"nZ5Ke","display_name":"mbutton15"},"value":46584,"didBreak":false},{"id":"GDXwdD","owner":{"id":"bNk2G","display_name":"Wickerznn \u26ab\u20e4"},"value":46740,"didBreak":false},{"id":"RM19aO","owner":{"id":"bDw4x","display_name":"Jamie"},"value":46969,"didBreak":false},{"id":"45Zdpl","owner":{"id":"nZQrd","display_name":"plush"},"value":47131,"didBreak":false},{"id":"jeN2xR","owner":{"id":"o2zOp","display_name":"ZanyZando"},"value":47182,"didBreak":false},{"id":"M5y4E9","owner":{"id":"A5JLg","display_name":"gijshomminga7"},"value":47314,"didBreak":false},{"id":"zJ2R7k","owner":{"id":"K81qp","display_name":"TucLTU"},"value":47469,"didBreak":false},{"id":"QmM8RL","owner":{"id":"nyJ4N","display_name":"coolninjaboyudude1234"},"value":47533,"didBreak":false},{"id":"a5qBJ3","owner":{"id":"4Lx4l","display_name":"eriks5955"},"value":47979,"didBreak":false},{"id":"JGvwkJ","owner":{"id":"ApW7Z","display_name":"M47145dg"},"value":48053,"didBreak":false},{"id":"B188yK","owner":{"id":"Apl69","display_name":"Donald5790"},"value":48119,"didBreak":false},{"id":"grWeWp","owner":{"id":"JDkWD","display_name":"Hentoad1"},"value":48162,"didBreak":false},{"id":"NdpW3N","owner":{"id":"Avqy4","display_name":"TojaKarol"},"value":48197,"didBreak":false},{"id":"JGymd7","owner":{"id":"ly9wR","display_name":"malizma333"},"value":48431,"didBreak":false},{"id":"M539dN","owner":{"id":"b1D1K","display_name":"BROTHER"},"value":48917,"didBreak":false},{"id":"ylMzXy","owner":{"id":"AgJOv","display_name":"uj030221-3551"},"value":49374,"didBreak":false},{"id":"rdQ16P","owner":{"id":"VPmjR","display_name":"0LL1"},"value":49473,"didBreak":false},{"id":"W4jej4","owner":{"id":"AaJLl","display_name":"palfly15"},"value":49812,"didBreak":false},{"id":"mKQ9kP","owner":{"id":"bqWeX","display_name":"."},"value":49857,"didBreak":false},{"id":"GDoyd9","owner":{"id":"9dW8x","display_name":"frotnight funy"},"value":50018,"didBreak":false},{"id":"Y3QNYQ","owner":{"id":"nRgg7","display_name":"XxTrollFacexX"},"value":50326,"didBreak":false},{"id":"M5l4N2","owner":{"id":"nQPB6","display_name":"LankyBoi"},"value":50373,"didBreak":false},{"id":"B1Qv97","owner":{"id":"AaoeX","display_name":"MageGeraint"},"value":50457,"didBreak":false},{"id":"3W47gB","owner":{"id":"nKBoL","display_name":"Murkaeus"},"value":50639,"didBreak":false},{"id":"oqqO3q","owner":{"id":"AWRGk","display_name":"\u6ed1\u5730\u4e0a\u4e4b\u5c0f\u7a3d"},"value":50753,"didBreak":false},{"id":"l52okL","owner":{"id":"VYB2y","display_name":"dylanwenger9"},"value":50803,"didBreak":false},{"id":"pQyMl8","owner":{"id":"AaqKe","display_name":"Pugloney29"},"value":50939,"didBreak":false},{"id":"ezMxWM","owner":{"id":"bmeEG","display_name":"Orbifold"},"value":51026,"didBreak":false},{"id":"GDoGRg","owner":{"id":"VwGgy","display_name":"cam"},"value":51101,"didBreak":false},{"id":"7lgwY7","owner":{"id":"Z3W4d","display_name":"zhaohuaye54"},"value":51103,"didBreak":false},{"id":"9ZQ27r","owner":{"id":"Y4mQ9","display_name":"Bram2323"},"value":51266,"didBreak":false},{"id":"8zG0G5","owner":{"id":"AvZPD","display_name":"Teh"},"value":51266,"didBreak":false},{"id":"6BBzlq","owner":{"id":"AWO1z","display_name":"Mr.ThisGuy"},"value":51579,"didBreak":false},{"id":"qY6D6P","owner":{"id":"b2Y9a","display_name":"Terra_Pringles"},"value":51846,"didBreak":false},{"id":"a5oKYa","owner":{"id":"bjrkJ","display_name":"gashpot"},"value":52022,"didBreak":false},{"id":"v8jlEy","owner":{"id":"xN3pP","display_name":"loganstephensmith"},"value":52211,"didBreak":false},{"id":"ylg0P3","owner":{"id":"33Qy4","display_name":"Cg089"},"value":52461,"didBreak":false},{"id":"QmvrZG","owner":{"id":"bqRNq","display_name":"Qthey"},"value":52484,"didBreak":false},{"id":"PeKJow","owner":{"id":"4LX0l","display_name":"Supernye"},"value":52530,"didBreak":false},{"id":"3WYNx9","owner":{"id":"dj944","display_name":"lee731017"},"value":52544,"didBreak":false},{"id":"daMNLB","owner":{"id":"VeN45","display_name":"Jeevus"},"value":52784,"didBreak":false},{"id":"qYMmpM","owner":{"id":"nRz77","display_name":"snowmaniac"},"value":53126,"didBreak":false},{"id":"l5zW37","owner":{"id":"p2MBw","display_name":"Jakke"},"value":53483,"didBreak":false},{"id":"6B8y3N","owner":{"id":"vMpo9","display_name":"Maistas"},"value":53695,"didBreak":false},{"id":"mKWdW9","owner":{"id":"bdXz7","display_name":"Aya"},"value":53782,"didBreak":false},{"id":"RM1rJ7","owner":{"id":"VPrKw","display_name":"nhaven14"},"value":53885,"didBreak":false},{"id":"PeKZmY","owner":{"id":"nRDjx","display_name":"HowieFTW"},"value":54291,"didBreak":false},{"id":"mKEZjW","owner":{"id":"q7dyW","display_name":"adamladam484"},"value":54381,"didBreak":false},{"id":"RM1Bg9","owner":{"id":"q7e4o","display_name":"Uniquepotatoes"},"value":54728,"didBreak":false},{"id":"RM7BoQ","owner":{"id":"bmW4E","display_name":"pome.\ud83d\ude08"},"value":54932,"didBreak":false},{"id":"5GGdo5","owner":{"id":"nKxxm","display_name":"Pengujedi"},"value":55107,"didBreak":false},{"id":"pQ9E12","owner":{"id":"bmvMP","display_name":"Shadow Blades"},"value":55107,"didBreak":false},{"id":"a5DE3l","owner":{"id":"JDQaJ","display_name":"spanner"},"value":55111,"didBreak":false},{"id":"ZLrJDl","owner":{"id":"p2v1o","display_name":"marcus.wasastjerna"},"value":55153,"didBreak":false},{"id":"45OLqM","owner":{"id":"nXM0Q","display_name":"hakejb1"},"value":55154,"didBreak":false},{"id":"0ZK20o","owner":{"id":"nR618","display_name":"Kn1GhT05"},"value":55208,"didBreak":false},{"id":"Op8adm","owner":{"id":"b8vqP","display_name":"Dragon Fruit"},"value":55219,"didBreak":false},{"id":"wMNJjm","owner":{"id":"Arv0Q","display_name":"Navet"},"value":55381,"didBreak":false},{"id":"l5ErMg","owner":{"id":"VJ32m","display_name":"rco915"},"value":55411,"didBreak":false},{"id":"EOaLRy","owner":{"id":"ABr6N","display_name":"Thudios"},"value":55556,"didBreak":false},{"id":"Ndg4JD","owner":{"id":"nR4vy","display_name":"Beefshankz"},"value":55815,"didBreak":false},{"id":"gr9pxE","owner":{"id":"bODpX","display_name":"Groovemouse"},"value":55839,"didBreak":false},{"id":"zJdRQ3","owner":{"id":"V6QoJ","display_name":"tomka700"},"value":55908,"didBreak":false},{"id":"l5rLB3","owner":{"id":"bdPo4","display_name":"smokedscrod"},"value":56118,"didBreak":false},{"id":"EOed6R","owner":{"id":"nQ4Rv","display_name":"razpe"},"value":56123,"didBreak":false},{"id":"RMvP7x","owner":{"id":"2WZgZ","display_name":"Katamari (old)"},"value":56372,"didBreak":false},{"id":"XZoYqa","owner":{"id":"AEeGD","display_name":"Slim"},"value":56526,"didBreak":false},{"id":"OpdqBm","owner":{"id":"A0Gze","display_name":"Bot Zket"},"value":56772,"didBreak":false},{"id":"l5NZvE","owner":{"id":"bdXQq","display_name":"Starstorm"},"value":56815,"didBreak":false},{"id":"v8jWxa","owner":{"id":"VYMJR","display_name":"dtee3"},"value":56955,"didBreak":false},{"id":"6B8EjD","owner":{"id":"VeRrM","display_name":"Chuek"},"value":56979,"didBreak":false},{"id":"Y3Qwgy","owner":{"id":"nR1NQ","display_name":"Valnix"},"value":56988,"didBreak":false},{"id":"k2oo3r","owner":{"id":"AgkRJ","display_name":"Miner_vdv"},"value":56988,"didBreak":false},{"id":"XZBKGz","owner":{"id":"XLo7Z","display_name":"TheRainCrow"},"value":57060,"didBreak":false},{"id":"45Z7GZ","owner":{"id":"AgBMK","display_name":"YottaCat"},"value":57179,"didBreak":false},{"id":"oqJ2Rj","owner":{"id":"bmYlr","display_name":"Catraption"},"value":57181,"didBreak":false},{"id":"W4Eqg4","owner":{"id":"A5jgd","display_name":"castigo"},"value":57237,"didBreak":false},{"id":"B1Q9g9","owner":{"id":"bxOWx","display_name":"SwordlessMimeTown"},"value":57412,"didBreak":false},{"id":"PewlEY","owner":{"id":"VeoE9","display_name":"E."},"value":57423,"didBreak":false},{"id":"M5yOPD","owner":{"id":"zodKM","display_name":"Moochywa"},"value":57483,"didBreak":false},{"id":"0ZE38r","owner":{"id":"jM3P5","display_name":"bille"},"value":57505,"didBreak":false},{"id":"LaED86","owner":{"id":"AG0zm","display_name":"315Lukas"},"value":57619,"didBreak":false},{"id":"3W5JYB","owner":{"id":"AGkwR","display_name":"theo.louesdon"},"value":57881,"didBreak":false},{"id":"mKQZom","owner":{"id":"bxEPx","display_name":"Azean"},"value":58023,"didBreak":false},{"id":"8zQadl","owner":{"id":"ABwl7","display_name":"Aklhys"},"value":58316,"didBreak":false},{"id":"DDLWp4","owner":{"id":"V6wN9","display_name":"rafaelcr44"},"value":58382,"didBreak":false},{"id":"XZdJg7","owner":{"id":"xNJv8","display_name":"Gibby"},"value":58443,"didBreak":false},{"id":"8zBq3m","owner":{"id":"A0P71","display_name":"Lord_F8L"},"value":58532,"didBreak":false},{"id":"oqD4dp","owner":{"id":"ABPyz","display_name":"_MooseCheese_"},"value":58597,"didBreak":false},{"id":"GDpRPD","owner":{"id":"RRe38","display_name":"Lorz"},"value":58747,"didBreak":false},{"id":"XZXoPe","owner":{"id":"A59D5","display_name":"KingIceCream"},"value":58856,"didBreak":false},{"id":"RMO29r","owner":{"id":"VeJB1","display_name":"Volardin"},"value":58880,"didBreak":false},{"id":"rdJZYX","owner":{"id":"vMze9","display_name":"Enredar1457"},"value":59005,"didBreak":false},{"id":"v8kGyP","owner":{"id":"o2ERX","display_name":"Waity5"},"value":59036,"didBreak":false},{"id":"ylQ038","owner":{"id":"AaKZB","display_name":"Zoom"},"value":59154,"didBreak":false},{"id":"Y3mQwl","owner":{"id":"Vl89p","display_name":"Kronos"},"value":59155,"didBreak":false},{"id":"ZLQd1X","owner":{"id":"bd997","display_name":"Marijn"},"value":59185,"didBreak":false},{"id":"KvQrom","owner":{"id":"VzMq3","display_name":"WiadrOrbaiW"},"value":59244,"didBreak":false},{"id":"k2zOyp","owner":{"id":"b72RP","display_name":"Smplstx"},"value":59320,"didBreak":false},{"id":"5GL2w4","owner":{"id":"A54WO","display_name":"Platypus"},"value":59340,"didBreak":false},{"id":"7lxpg1","owner":{"id":"nRQXy","display_name":"zerd"},"value":59382,"didBreak":false},{"id":"pQjo5w","owner":{"id":"Vzx1Y","display_name":"Doggo"},"value":59402,"didBreak":false},{"id":"pQ1zp8","owner":{"id":"bO8Xm","display_name":"endy80"},"value":59406,"didBreak":false},{"id":"La306z","owner":{"id":"N5vwK","display_name":"ancovd12"},"value":59413,"didBreak":false},{"id":"3W12oO","owner":{"id":"b7N6z","display_name":"superneuras"},"value":59461,"didBreak":false},{"id":"zJg64M","owner":{"id":"nRawr","display_name":"AkillezII"},"value":59507,"didBreak":false},{"id":"pQQGN1","owner":{"id":"W7ZMe","display_name":"rainy"},"value":59587,"didBreak":false},{"id":"pQW8ed","owner":{"id":"gXXXO","display_name":"\u272a tom1911"},"value":59612,"didBreak":false},{"id":"qY6m34","owner":{"id":"vMlrD","display_name":"cornshitfuck"},"value":59665,"didBreak":false},{"id":"Kvvmkk","owner":{"id":"AaDNX","display_name":"Go Seigen"},"value":59761,"didBreak":false},{"id":"rd92rJ","owner":{"id":"b8Jkl","display_name":"Sloane"},"value":59787,"didBreak":false},{"id":"Pepqal","owner":{"id":"Vz87D","display_name":"Kastrull"},"value":59792,"didBreak":false},{"id":"OpmqxB","owner":{"id":"bOoQB","display_name":"Bushy"},"value":59825,"didBreak":false},{"id":"wMyGXO","owner":{"id":"bdM2B","display_name":"BorkFanBoy"},"value":59842,"didBreak":false},{"id":"RMOL8e","owner":{"id":"bd2PR","display_name":"gundu_001"},"value":59853,"didBreak":false},{"id":"rdKN4J","owner":{"id":"AogYX","display_name":"Caligula"},"value":59884,"didBreak":false},{"id":"pQ6LXw","owner":{"id":"VlxvR","display_name":"Birnfeld"},"value":59891,"didBreak":false},{"id":"qY60jl","owner":{"id":"zoJYX","display_name":"GolEden"},"value":59948,"didBreak":false},{"id":"grNG7K","owner":{"id":"VzP4D","display_name":"Frits"},"value":60016,"didBreak":false},{"id":"W4O4OO","owner":{"id":"b7BDz","display_name":"Mulalu"},"value":60025,"didBreak":false},{"id":"8zmjL5","owner":{"id":"nR1Je","display_name":"Qcrist"},"value":60048,"didBreak":false},{"id":"l5QjEj","owner":{"id":"b21WG","display_name":"Hyppis"},"value":60050,"didBreak":false},{"id":"v8qw7L","owner":{"id":"VlqWL","display_name":"Skriban"},"value":60089,"didBreak":false},{"id":"45W4MK","owner":{"id":"nRNB2","display_name":"BuildingDR"},"value":60115,"didBreak":false},{"id":"ezRRm9","owner":{"id":"bN7JG","display_name":"AZ-LT"},"value":60156,"didBreak":false},{"id":"Peg35R","owner":{"id":"VY6rQ","display_name":"The Toasted Marshmallow"},"value":60214,"didBreak":false},{"id":"yllGKR","owner":{"id":"VlMk3","display_name":"RisingStar"},"value":60216,"didBreak":false},{"id":"jeJqqm","owner":{"id":"bm59L","display_name":"siDohK"},"value":60251,"didBreak":false},{"id":"Y3Gkxz","owner":{"id":"e37m9","display_name":"Teywer"},"value":60273,"didBreak":false},{"id":"GDR3OD","owner":{"id":"b29Kk","display_name":"pineapplebacon777"},"value":60295,"didBreak":false},{"id":"a5KxjK","owner":{"id":"xNEB5","display_name":"DudeGuy04"},"value":60295,"didBreak":false},{"id":"5G6WPZ","owner":{"id":"b712w","display_name":"schwiftyking"},"value":60312,"didBreak":false},{"id":"7lgedx","owner":{"id":"VJYmJ","display_name":"Typodestoyer"},"value":60314,"didBreak":false},{"id":"l5B1eP","owner":{"id":"QO5yv","display_name":"LUCse MENSEN"},"value":60360,"didBreak":false},{"id":"W4M9Je","owner":{"id":"Aa2El","display_name":"Matty90509"},"value":60368,"didBreak":false},{"id":"RM7KRO","owner":{"id":"nKEG3","display_name":"BOYAR"},"value":60380,"didBreak":false},{"id":"zJdJ9Y","owner":{"id":"Z3Nxl","display_name":"jakers0011"},"value":60388,"didBreak":false},{"id":"GDpaDw","owner":{"id":"b1gOK","display_name":"Existence is Pain"},"value":60423,"didBreak":false},{"id":"GD8K89","owner":{"id":"VeJO1","display_name":"\u6e05\u6e05\u82b1\u72f8\u732b"},"value":60446,"didBreak":false},{"id":"l5zg6P","owner":{"id":"7Rzez","display_name":"Loner"},"value":60454,"didBreak":false},{"id":"oqE0d6","owner":{"id":"nLRN9","display_name":"Fockey15"},"value":60484,"didBreak":false},{"id":"9Z7kLx","owner":{"id":"a7Kda","display_name":"Outragedgamer14"},"value":60513,"didBreak":false},{"id":"jeENMp","owner":{"id":"b209D","display_name":"~ Smithy ~"},"value":60513,"didBreak":false},{"id":"ez39dQ","owner":{"id":"Lmd3w","display_name":"Whyit1"},"value":60533,"didBreak":false},{"id":"qYxl6X","owner":{"id":"b7w86","display_name":"vkelloku"},"value":60569,"didBreak":false},{"id":"grNE8e","owner":{"id":"nygK7","display_name":"kristoffer"},"value":60625,"didBreak":false},{"id":"pQRLk2","owner":{"id":"1q0PK","display_name":"joseph.pesqui"},"value":60642,"didBreak":false},{"id":"45aM0M","owner":{"id":"6qr1D","display_name":"Oddysen"},"value":60662,"didBreak":false},{"id":"LagGKR","owner":{"id":"AaXLe","display_name":"jacob.hh"},"value":60686,"didBreak":false},{"id":"0ZEP8w","owner":{"id":"AGp6g","display_name":"SpandexN00dle"},"value":60707,"didBreak":false},{"id":"PeGKyw","owner":{"id":"nXWw7","display_name":"Diggsey"},"value":60746,"didBreak":false},{"id":"GDXrDq","owner":{"id":"nQ6Be","display_name":"I Like Ugly Mammals."},"value":60801,"didBreak":false},{"id":"7lLKlz","owner":{"id":"b8LXR","display_name":"celesteal"},"value":60826,"didBreak":false},{"id":"0ZK9Jj","owner":{"id":"nXd2E","display_name":"Kubu\u015b :*"},"value":60828,"didBreak":false},{"id":"ylQ8W6","owner":{"id":"OBwWJ","display_name":"GeGe"},"value":60831,"didBreak":false},{"id":"2Zq9Zw","owner":{"id":"b3v8L","display_name":"Toto00"},"value":60835,"didBreak":false},{"id":"Y3qNL3","owner":{"id":"Aawpa","display_name":"geroniberry"},"value":60850,"didBreak":false},{"id":"Qm6jpO","owner":{"id":"N559o","display_name":"7DimensionalParrot"},"value":60858,"didBreak":false},{"id":"Y3E6Zl","owner":{"id":"VPMeX","display_name":"DildoBike"},"value":60869,"didBreak":false},{"id":"LampWa","owner":{"id":"b1QmX","display_name":"chenail.liam"},"value":60898,"didBreak":false},{"id":"k2mXDr","owner":{"id":"VPQRY","display_name":"R"},"value":60903,"didBreak":false},{"id":"PeG8aX","owner":{"id":"AGRgD","display_name":"Bull Moose"},"value":60909,"didBreak":false},{"id":"2ZzBZJ","owner":{"id":"bNPZo","display_name":"Big Dick Brian"},"value":60911,"didBreak":false},{"id":"oqY9O5","owner":{"id":"nkd9R","display_name":"Oreocraft2"},"value":60938,"didBreak":false},{"id":"LaDloz","owner":{"id":"9dwLJ","display_name":"Kalorienreduziert"},"value":60954,"didBreak":false},{"id":"v8XDQ1","owner":{"id":"b2Q0w","display_name":"Luna Kampling"},"value":60956,"didBreak":false},{"id":"XZov6D","owner":{"id":"Ag9ae","display_name":"CoolCorps"},"value":60966,"didBreak":false},{"id":"7l0241","owner":{"id":"nZ47X","display_name":"Ogremor"},"value":60971,"didBreak":false},{"id":"8zGREa","owner":{"id":"EBzP2","display_name":"lollyH2O"},"value":60994,"didBreak":false},{"id":"QmoeN4","owner":{"id":"Vw7oR","display_name":"Salty Snail"},"value":60997,"didBreak":false},{"id":"B17elR","owner":{"id":"Vzl1G","display_name":"timmyaustin29.as"},"value":60998,"didBreak":false},{"id":"mKWm0r","owner":{"id":"AMxzX","display_name":"bumperdo09"},"value":61000,"didBreak":false},{"id":"jeDYr7","owner":{"id":"a7OjO","display_name":"tetsu_yamamon"},"value":61000,"didBreak":false},{"id":"ezBMvz","owner":{"id":"A0wve","display_name":"Cupar Guy"},"value":71516,"didBreak":false}],"metadata":{"uniqueRanksCount":285}}}