{"any":{"top1000":[{"id":"pQ93Ko","owner":{"id":"p269o","display_name":"david.c.hagglund"},"value":61996,"didBreak":true},{"id":"DDQMr9","owner":{"id":"VeRvv","display_name":"I never finish anyth"},"value":66444,"didBreak":false},{"id":"8z05Kl","owner":{"id":"nR1RO","display_name":"Soba"},"value":67344,"didBreak":false},{"id":"7lyMZP","owner":{"id":"JDKZ5","display_name":"gold torizo"},"value":69292,"didBreak":false},{"id":"qY3z7e","owner":{"id":"klz3a","display_name":"Heater"},"value":71469,"didBreak":false},{"id":"dazrmR","owner":{"id":"VzNRW","display_name":"goldenpggie"},"value":72460,"didBreak":true},{"id":"zJO6mY","owner":{"id":"33Gg4","display_name":"Sandor Of The MIsts"},"value":73973,"didBreak":false},{"id":"M5lPN9","owner":{"id":"bqWeX","display_name":"."},"value":76057,"didBreak":true},{"id":"0ZpRrw","owner":{"id":"bd3zw","display_name":"olivapaa"},"value":77232,"didBreak":false},{"id":"JGKjPB","owner":{"id":"Pgkdl","display_name":"Arak'nae"},"value":78778,"didBreak":false},{"id":"GDE59x","owner":{"id":"4Lx4l","display_name":"eriks5955"},"value":78944,"didBreak":false},{"id":"9Z5zWJ","owner":{"id":"dj944","display_name":"lee731017"},"value":80646,"didBreak":true},{"id":"qYxJOJ","owner":{"id":"nXdED","display_name":"gl_zhu"},"value":81807,"didBreak":false},{"id":"45Xea8","owner":{"id":"Ap15m","display_name":"Looming"},"value":82374,"didBreak":false},{"id":"qYMg2q","owner":{"id":"rlD0P","display_name":"Jacowboy"},"value":82620,"didBreak":false},{"id":"v86NLy","owner":{"id":"V6J3Z","display_name":"oubeidong"},"value":83909,"didBreak":false},{"id":"v8p3EP","owner":{"id":"b1zzK","display_name":"Trygeve"},"value":85472,"didBreak":false},{"id":"k2NokR","owner":{"id":"nRNB2","display_name":"BuildingDR"},"value":86430,"didBreak":false},{"id":"M5dqQd","owner":{"id":"bj0x5","display_name":"Danielos"},"value":86845,"didBreak":false},{"id":"7l01Mj","owner":{"id":"V6w9Z","display_name":"Draradech"},"value":87401,"didBreak":false},{"id":"0ZOG9j","owner":{"id":"gXN5E","display_name":"CasualSanta"},"value":87921,"didBreak":false},{"id":"ezpQ4z","owner":{"id":"VeqyJ","display_name":"Dregu"},"value":88000,"didBreak":false},{"id":"wMB4dz","owner":{"id":"bmYlr","display_name":"Catraption"},"value":89982,"didBreak":false},{"id":"3WRNXB","owner":{"id":"VzMq3","display_name":"WiadrOrbaiW"},"value":91661,"didBreak":false},{"id":"yl2Jd8","owner":{"id":"nZN82","display_name":"\u263c \u263c \u263c"},"value":92687,"didBreak":false},{"id":"W40O2k","owner":{"id":"nLqJ9","display_name":"Kirby Kidd"},"value":94036,"didBreak":true},{"id":"XZowGZ","owner":{"id":"b8LXR","display_name":"celesteal"},"value":94289,"didBreak":true},{"id":"DD8QjP","owner":{"id":"nZ5Ke","display_name":"mbutton15"},"value":95062,"didBreak":false},{"id":"ezMpY1","owner":{"id":"mwxYW","display_name":"Maruka"},"value":95408,"didBreak":false},{"id":"pQKEZR","owner":{"id":"LmzoD","display_name":"seutimsyab"},"value":95441,"didBreak":false},{"id":"0Z4G2o","owner":{"id":"AWO1z","display_name":"Mr.ThisGuy"},"value":95473,"didBreak":false},{"id":"l5ENJ7","owner":{"id":"ArkGJ","display_name":"veggie stix"},"value":96763,"didBreak":false},{"id":"l59XG2","owner":{"id":"VJ5zK","display_name":"jonaTHOT"},"value":97419,"didBreak":false},{"id":"ezRGoM","owner":{"id":"AgJOv","display_name":"uj030221-3551"},"value":97788,"didBreak":false},{"id":"EO9Prx","owner":{"id":"nRJR7","display_name":"Mizuhana"},"value":99976,"didBreak":false},{"id":"45ZzGK","owner":{"id":"nZBPe","display_name":"HiCanIKillYou"},"value":100605,"didBreak":false},{"id":"x3wdN1","owner":{"id":"AaoBM","display_name":"Linuxx\ue066"},"value":102123,"didBreak":true},{"id":"dazNwK","owner":{"id":"gXXXO","display_name":"\u272a tom1911"},"value":102136,"didBreak":false},{"id":"5GdOpx","owner":{"id":"b7oO6","display_name":"Rico The Saboteur"},"value":102775,"didBreak":false},{"id":"qYWxBo","owner":{"id":"OBwWJ","display_name":"GeGe"},"value":103115,"didBreak":false},{"id":"k2mrmp","owner":{"id":"bxEPx","display_name":"Azean"},"value":103558,"didBreak":false},{"id":"1W7KQ0","owner":{"id":"A5lL4","display_name":"Geert wilders"},"value":103961,"didBreak":true},{"id":"daayWq","owner":{"id":"nQML4","display_name":"Honn"},"value":104133,"didBreak":false},{"id":"W7WpQ1","owner":{"id":"bdlWR","display_name":"popcorniosaurus"},"value":104206,"didBreak":true},{"id":"QmgXqY","owner":{"id":"AMk3N","display_name":"lionale29ten"},"value":104758,"didBreak":false},{"id":"rdJlNL","owner":{"id":"A5jgd","display_name":"castigo"},"value":104854,"didBreak":false},{"id":"DD5vP9","owner":{"id":"RRmE2","display_name":"piccolo_SPA"},"value":105106,"didBreak":true},{"id":"B1gMzm","owner":{"id":"AaKBO","display_name":"BronBerry"},"value":105229,"didBreak":false},{"id":"grYeKE","owner":{"id":"V6wmJ","display_name":"Fabi\u2b50\ufe0fCst"},"value":105846,"didBreak":false},{"id":"3WaNJD","owner":{"id":"VJ5OW","display_name":"BaconPancakes"},"value":105932,"didBreak":false},{"id":"qYNdzX","owner":{"id":"ArwmL","display_name":"Freedom_IT"},"value":106000,"didBreak":false},{"id":"7lXz43","owner":{"id":"nLRN9","display_name":"Fockey15"},"value":106011,"didBreak":false},{"id":"2Z7gJw","owner":{"id":"b3NwR","display_name":"hopstalgic"},"value":106343,"didBreak":false},{"id":"mKY8WW","owner":{"id":"A59w7","display_name":"aBacIdEe"},"value":106493,"didBreak":false},{"id":"2ZQ8Nk","owner":{"id":"Aowaq","display_name":"Thoomor"},"value":106732,"didBreak":false},{"id":"oq6zO3","owner":{"id":"bNPZo","display_name":"Big Dick Brian"},"value":106747,"didBreak":false},{"id":"6B3Waj","owner":{"id":"p2rj1","display_name":"Strawman"},"value":107073,"didBreak":false},{"id":"k267QD","owner":{"id":"Vw5QR","display_name":"marciochb"},"value":107073,"didBreak":true},{"id":"pQNrlw","owner":{"id":"bqG1P","display_name":"Jujublackmagic"},"value":107271,"didBreak":false},{"id":"9Zwqrx","owner":{"id":"V6QoJ","display_name":"tomka700"},"value":107467,"didBreak":false},{"id":"daM5or","owner":{"id":"5QLzZ","display_name":"arvin900"},"value":107622,"didBreak":false},{"id":"ZLweWe","owner":{"id":"AGR7w","display_name":"Bubi"},"value":107914,"didBreak":false},{"id":"RMx9r7","owner":{"id":"nRawr","display_name":"AkillezII"},"value":107922,"didBreak":false},{"id":"ZLK8Ky","owner":{"id":"e37m9","display_name":"Teywer"},"value":108048,"didBreak":false},{"id":"EOYzWo","owner":{"id":"Y44Pl","display_name":"Realyum"},"value":108500,"didBreak":false},{"id":"grrrgM","owner":{"id":"AaDNX","display_name":"Go Seigen"},"value":108578,"didBreak":false},{"id":"8zdkvw","owner":{"id":"1qPza","display_name":"MBS4444"},"value":108825,"didBreak":false},{"id":"RMa58O","owner":{"id":"bm9Pm","display_name":"SmileyFace799"},"value":108900,"didBreak":false},{"id":"ezNoB5","owner":{"id":"VzP4D","display_name":"Frits"},"value":109040,"didBreak":true},{"id":"KvD5m9","owner":{"id":"xNJv8","display_name":"Gibby"},"value":109092,"didBreak":true},{"id":"2Zlewk","owner":{"id":"nXM0Q","display_name":"hakejb1"},"value":109120,"didBreak":true},{"id":"daMq17","owner":{"id":"yX9za","display_name":"Kuato"},"value":109241,"didBreak":false},{"id":"QmDDgL","owner":{"id":"bmvMP","display_name":"Shadow Blades"},"value":109264,"didBreak":false},{"id":"5GPEYO","owner":{"id":"AMrq9","display_name":"Jormungandr"},"value":109289,"didBreak":false},{"id":"qY6Qe4","owner":{"id":"nR4vy","display_name":"Beefshankz"},"value":109295,"didBreak":false},{"id":"6BWZZ9","owner":{"id":"bOgdW","display_name":"liquor snurf"},"value":109345,"didBreak":false},{"id":"Qm63lv","owner":{"id":"VlqWL","display_name":"Skriban"},"value":109460,"didBreak":false},{"id":"0ZKXrM","owner":{"id":"b712w","display_name":"schwiftyking"},"value":109468,"didBreak":false},{"id":"ylg0pR","owner":{"id":"yXBGa","display_name":"wumengyundf"},"value":109474,"didBreak":false},{"id":"daWwm4","owner":{"id":"b8x6O","display_name":"233333"},"value":109516,"didBreak":false},{"id":"k2zqeD","owner":{"id":"AWRGk","display_name":"\u6ed1\u5730\u4e0a\u4e4b\u5c0f\u7a3d"},"value":109521,"didBreak":true},{"id":"rd65RL","owner":{"id":"VwGgy","display_name":"cam"},"value":109569,"didBreak":false},{"id":"DDxMqy","owner":{"id":"VJ4X7","display_name":"minecat"},"value":109719,"didBreak":false},{"id":"ezaXjE","owner":{"id":"nLdwR","display_name":"chrisrothenhoefer"},"value":109834,"didBreak":false},{"id":"GDvOvR","owner":{"id":"Arrk3","display_name":"davidloh"},"value":109853,"didBreak":false},{"id":"grBQP6","owner":{"id":"Z3W4d","display_name":"zhaohuaye54"},"value":109869,"didBreak":true},{"id":"JGoxED","owner":{"id":"A0Gze","display_name":"Bot Zket"},"value":109908,"didBreak":false},{"id":"zJ2GgM","owner":{"id":"p2MBw","display_name":"Jakke"},"value":109995,"didBreak":false},{"id":"v8zr15","owner":{"id":"bxPL7","display_name":"KiQui"},"value":110006,"didBreak":false},{"id":"GDBEKm","owner":{"id":"VJk8J","display_name":"TTV\/fingeon27"},"value":110121,"didBreak":false},{"id":"wMy10o","owner":{"id":"Pg2Dk","display_name":"Craze"},"value":110152,"didBreak":false},{"id":"5GeyNZ","owner":{"id":"9dwLJ","display_name":"Kalorienreduziert"},"value":110209,"didBreak":false},{"id":"GDBXO9","owner":{"id":"nQ6Be","display_name":"I Like Ugly Mammals."},"value":110228,"didBreak":false},{"id":"gr06Ev","owner":{"id":"vMlrD","display_name":"cornshitfuck"},"value":110238,"didBreak":false},{"id":"9ZmDay","owner":{"id":"VPrKw","display_name":"nhaven14"},"value":110239,"didBreak":false},{"id":"ezJQWa","owner":{"id":"EBzP2","display_name":"lollyH2O"},"value":110273,"didBreak":true},{"id":"GDB3Eq","owner":{"id":"nRQXy","display_name":"zerd"},"value":110277,"didBreak":true},{"id":"1WGO3P","owner":{"id":"V6v2a","display_name":"TobyDog"},"value":110311,"didBreak":false},{"id":"3W6gBD","owner":{"id":"JDMOK","display_name":"tokki10"},"value":110315,"didBreak":false},{"id":"GDBoy6","owner":{"id":"AaKZB","display_name":"Zoom"},"value":110331,"didBreak":false},{"id":"k219B4","owner":{"id":"nXWw7","display_name":"Diggsey"},"value":110331,"didBreak":false},{"id":"RMmdl8","owner":{"id":"bd2PR","display_name":"gundu_001"},"value":110332,"didBreak":false},{"id":"grBmwM","owner":{"id":"nXd2E","display_name":"Kubu\u015b :*"},"value":110411,"didBreak":false},{"id":"v86L95","owner":{"id":"nZqEl","display_name":"thueman"},"value":110456,"didBreak":false},{"id":"3WJBeD","owner":{"id":"nRlNe","display_name":"iRevErse Cs"},"value":110496,"didBreak":false},{"id":"zJRke3","owner":{"id":"b8EaP","display_name":"Peppsy"},"value":110498,"didBreak":false},{"id":"KvyGQL","owner":{"id":"a7N6a","display_name":"Bem"},"value":110516,"didBreak":false},{"id":"v8jD0a","owner":{"id":"VPMeX","display_name":"DildoBike"},"value":110517,"didBreak":false},{"id":"5GBKp7","owner":{"id":"bNL9G","display_name":"crocka123"},"value":110537,"didBreak":false},{"id":"k2d1Rp","owner":{"id":"N559o","display_name":"7DimensionalParrot"},"value":110544,"didBreak":false},{"id":"5GaDop","owner":{"id":"VlPW4","display_name":"Stabhole"},"value":110558,"didBreak":false},{"id":"W4K60e","owner":{"id":"ABr6N","display_name":"Thudios"},"value":110595,"didBreak":false},{"id":"8zwDQw","owner":{"id":"mwoE9","display_name":"Mikie"},"value":110603,"didBreak":false},{"id":"Ndga9D","owner":{"id":"AGwPo","display_name":"FrankNirvana"},"value":110611,"didBreak":false},{"id":"oqQWK3","owner":{"id":"e3yez","display_name":"Krazy Koi Fish"},"value":110637,"didBreak":false},{"id":"qYMGeJ","owner":{"id":"Apl69","display_name":"Donald5790"},"value":110653,"didBreak":false},{"id":"l5EEdR","owner":{"id":"2WZgZ","display_name":"Katamari (old)"},"value":110654,"didBreak":false},{"id":"1WGqX0","owner":{"id":"q7MYq","display_name":"jbmisi14"},"value":110656,"didBreak":false},{"id":"JGy7XW","owner":{"id":"bxO05","display_name":"xBrowi"},"value":110658,"didBreak":false},{"id":"W4O6kz","owner":{"id":"b29Kk","display_name":"pineapplebacon777"},"value":110667,"didBreak":false},{"id":"GDRQYw","owner":{"id":"nKBoL","display_name":"Murkaeus"},"value":110684,"didBreak":false},{"id":"Pey6aQ","owner":{"id":"AGkwR","display_name":"theo.louesdon"},"value":110697,"didBreak":false},{"id":"zJ8wjG","owner":{"id":"bdlZ4","display_name":"CkyNik"},"value":110710,"didBreak":false},{"id":"pQ9Yg5","owner":{"id":"p2v1o","display_name":"marcus.wasastjerna"},"value":110747,"didBreak":false},{"id":"a5NyDB","owner":{"id":"9dW8x","display_name":"frotnight funy"},"value":110750,"didBreak":false},{"id":"zJO7B7","owner":{"id":"ABwl7","display_name":"Aklhys"},"value":110758,"didBreak":false},{"id":"OpvQ3a","owner":{"id":"nyJ4N","display_name":"coolninjaboyudude1234"},"value":110763,"didBreak":false},{"id":"RM65ex","owner":{"id":"b72RP","display_name":"Smplstx"},"value":110765,"didBreak":false},{"id":"9Z7Rqr","owner":{"id":"VPQRY","display_name":"R"},"value":110771,"didBreak":false},{"id":"5GZxq4","owner":{"id":"a7Kda","display_name":"Outragedgamer14"},"value":110778,"didBreak":false},{"id":"3W4JE8","owner":{"id":"bd997","display_name":"Marijn"},"value":110787,"didBreak":false},{"id":"RM6XP7","owner":{"id":"K81qp","display_name":"TucLTU"},"value":110787,"didBreak":true},{"id":"PeK4WQ","owner":{"id":"nygK7","display_name":"kristoffer"},"value":110794,"didBreak":false},{"id":"GDB3Wo","owner":{"id":"AogYX","display_name":"Caligula"},"value":110797,"didBreak":false},{"id":"qYjreP","owner":{"id":"b8Jkl","display_name":"Sloane"},"value":110802,"didBreak":false},{"id":"JG8OD7","owner":{"id":"b7w86","display_name":"vkelloku"},"value":110854,"didBreak":false},{"id":"daWK7G","owner":{"id":"b1vyY","display_name":"zezetel"},"value":110854,"didBreak":true},{"id":"EOvLYP","owner":{"id":"nyMj3","display_name":"Hazmat"},"value":110857,"didBreak":false},{"id":"l5Wm0P","owner":{"id":"Ag9yv","display_name":"DuuSuu"},"value":110859,"didBreak":false},{"id":"RMDaJr","owner":{"id":"AG0zm","display_name":"315Lukas"},"value":110870,"didBreak":false},{"id":"x3jyjP","owner":{"id":"b7BDz","display_name":"Mulalu"},"value":110881,"didBreak":false},{"id":"RMN9x2","owner":{"id":"1q0PK","display_name":"joseph.pesqui"},"value":110890,"didBreak":false},{"id":"k22xjp","owner":{"id":"W7ZMe","display_name":"rainy"},"value":110893,"didBreak":false},{"id":"8zd0gO","owner":{"id":"nXBXz","display_name":"lazy comet"},"value":110898,"didBreak":false},{"id":"PeMNal","owner":{"id":"vMpo9","display_name":"Maistas"},"value":110900,"didBreak":false},{"id":"RMD83j","owner":{"id":"K8eN0","display_name":"-1-1-"},"value":110900,"didBreak":false},{"id":"zJzLLo","owner":{"id":"AGRgD","display_name":"Bull Moose"},"value":110908,"didBreak":false},{"id":"dazlEG","owner":{"id":"AaJLl","display_name":"palfly15"},"value":110925,"didBreak":false},{"id":"daKzv4","owner":{"id":"bmW4E","display_name":"pome.\ud83d\ude08"},"value":110932,"didBreak":false},{"id":"JG44ZJ","owner":{"id":"bN7JG","display_name":"AZ-LT"},"value":110939,"didBreak":false},{"id":"OpQx2R","owner":{"id":"n90yJ","display_name":"Aviven11"},"value":110939,"didBreak":false},{"id":"pQ1LY8","owner":{"id":"q72do","display_name":"True SmolSir"},"value":110946,"didBreak":false},{"id":"daoELd","owner":{"id":"VlMk3","display_name":"RisingStar"},"value":110950,"didBreak":false},{"id":"qY7yGJ","owner":{"id":"b1QmX","display_name":"chenail.liam"},"value":110957,"didBreak":false},{"id":"7lWBqR","owner":{"id":"b8Z7l","display_name":"Fiku121"},"value":110964,"didBreak":false},{"id":"PejwQl","owner":{"id":"b21WG","display_name":"Hyppis"},"value":110983,"didBreak":false},{"id":"9Z0w2x","owner":{"id":"b1EWK","display_name":"lukas.bornheim"},"value":110986,"didBreak":false},{"id":"8zgEra","owner":{"id":"bjk4J","display_name":"duvald16"},"value":110988,"didBreak":false},{"id":"pQRDzR","owner":{"id":"nRgg7","display_name":"XxTrollFacexX"},"value":110989,"didBreak":false},{"id":"v8k9Op","owner":{"id":"AWwNk","display_name":"iwantmore29"},"value":110991,"didBreak":false},{"id":"l51E3R","owner":{"id":"nQ4Rv","display_name":"razpe"},"value":110994,"didBreak":false},{"id":"ezM4oa","owner":{"id":"nZQrd","display_name":"plush"},"value":110996,"didBreak":false},{"id":"wM110y","owner":{"id":"bdPo4","display_name":"smokedscrod"},"value":110997,"didBreak":false},{"id":"qYNJKq","owner":{"id":"A5JLg","display_name":"gijshomminga7"},"value":110997,"didBreak":false},{"id":"M5lPKM","owner":{"id":"q7e4o","display_name":"Uniquepotatoes"},"value":110998,"didBreak":false},{"id":"5G3ykx","owner":{"id":"bdXQq","display_name":"Starstorm"},"value":110998,"didBreak":false},{"id":"a5NzkX","owner":{"id":"Aa2El","display_name":"Matty90509"},"value":110999,"didBreak":false},{"id":"XZaa4Z","owner":{"id":"bOoQB","display_name":"Bushy"},"value":111000,"didBreak":false},{"id":"B12r4d","owner":{"id":"bODpX","display_name":"Groovemouse"},"value":111000,"didBreak":false},{"id":"ZLargO","owner":{"id":"Vz87D","display_name":"Kastrull"},"value":111000,"didBreak":false},{"id":"l594m3","owner":{"id":"QOmOe","display_name":"arronon"},"value":111000,"didBreak":false},{"id":"PeNyql","owner":{"id":"AaqKe","display_name":"Pugloney29"},"value":111000,"didBreak":false},{"id":"LaEe9l","owner":{"id":"a7OjO","display_name":"tetsu_yamamon"},"value":111000,"didBreak":false},{"id":"da0qvB","owner":{"id":"ArX03","display_name":"FusedZirconium"},"value":115677,"didBreak":true},{"id":"ezyWwa","owner":{"id":"b3Gq3","display_name":"colinblue57"},"value":130526,"didBreak":false},{"id":"8zdzQL","owner":{"id":"AG29x","display_name":"Frit\u00f6senfett Fred"},"value":157218,"didBreak":false},{"id":"qYZKPL","owner":{"id":"Arv0Q","display_name":"Navet"},"value":160622,"didBreak":false},{"id":"rdXMmW","owner":{"id":"Aawpa","display_name":"geroniberry"},"value":162432,"didBreak":true},{"id":"M53wJ2","owner":{"id":"ABvZ9","display_name":"twistedsister86"},"value":192512,"didBreak":true},{"id":"jeozkR","owner":{"id":"b2Y9a","display_name":"Terra_Pringles"},"value":215125,"didBreak":false}],"metadata":{"uniqueRanksCount":251}},"unbroken":{"top1000":[{"id":"DDQMr9","owner":{"id":"VeRvv","display_name":"I never finish anyth"},"value":66444,"didBreak":false},{"id":"8z05Kl","owner":{"id":"nR1RO","display_name":"Soba"},"value":67344,"didBreak":false},{"id":"7lyMZP","owner":{"id":"JDKZ5","display_name":"gold torizo"},"value":69292,"didBreak":false},{"id":"qY3z7e","owner":{"id":"klz3a","display_name":"Heater"},"value":71469,"didBreak":false},{"id":"zJO6mY","owner":{"id":"33Gg4","display_name":"Sandor Of The MIsts"},"value":73973,"didBreak":false},{"id":"dazRMr","owner":{"id":"p269o","display_name":"david.c.hagglund"},"value":75375,"didBreak":false},{"id":"0ZpRrw","owner":{"id":"bd3zw","display_name":"olivapaa"},"value":77232,"didBreak":false},{"id":"JGKjPB","owner":{"id":"Pgkdl","display_name":"Arak'nae"},"value":78778,"didBreak":false},{"id":"GDE59x","owner":{"id":"4Lx4l","display_name":"eriks5955"},"value":78944,"didBreak":false},{"id":"daqvo7","owner":{"id":"dj944","display_name":"lee731017"},"value":80657,"didBreak":false},{"id":"qYxJOJ","owner":{"id":"nXdED","display_name":"gl_zhu"},"value":81807,"didBreak":false},{"id":"45Xea8","owner":{"id":"Ap15m","display_name":"Looming"},"value":82374,"didBreak":false},{"id":"qYMg2q","owner":{"id":"rlD0P","display_name":"Jacowboy"},"value":82620,"didBreak":false},{"id":"v86NLy","owner":{"id":"V6J3Z","display_name":"oubeidong"},"value":83909,"didBreak":false},{"id":"v8p3EP","owner":{"id":"b1zzK","display_name":"Trygeve"},"value":85472,"didBreak":false},{"id":"k2NokR","owner":{"id":"nRNB2","display_name":"BuildingDR"},"value":86430,"didBreak":false},{"id":"M5dqQd","owner":{"id":"bj0x5","display_name":"Danielos"},"value":86845,"didBreak":false},{"id":"7l01Mj","owner":{"id":"V6w9Z","display_name":"Draradech"},"value":87401,"didBreak":false},{"id":"0ZOG9j","owner":{"id":"gXN5E","display_name":"CasualSanta"},"value":87921,"didBreak":false},{"id":"ezpQ4z","owner":{"id":"VeqyJ","display_name":"Dregu"},"value":88000,"didBreak":false},{"id":"wMB4dz","owner":{"id":"bmYlr","display_name":"Catraption"},"value":89982,"didBreak":false},{"id":"3WRNXB","owner":{"id":"VzMq3","display_name":"WiadrOrbaiW"},"value":91661,"didBreak":false},{"id":"yl2Jd8","owner":{"id":"nZN82","display_name":"\u263c \u263c \u263c"},"value":92687,"didBreak":false},{"id":"DD8QjP","owner":{"id":"nZ5Ke","display_name":"mbutton15"},"value":95062,"didBreak":false},{"id":"ezMpY1","owner":{"id":"mwxYW","display_name":"Maruka"},"value":95408,"didBreak":false},{"id":"pQKEZR","owner":{"id":"LmzoD","display_name":"seutimsyab"},"value":95441,"didBreak":false},{"id":"0Z4G2o","owner":{"id":"AWO1z","display_name":"Mr.ThisGuy"},"value":95473,"didBreak":false},{"id":"W4KPll","owner":{"id":"nLqJ9","display_name":"Kirby Kidd"},"value":96051,"didBreak":false},{"id":"JG8p34","owner":{"id":"VzNRW","display_name":"goldenpggie"},"value":96237,"didBreak":false},{"id":"l5ENJ7","owner":{"id":"ArkGJ","display_name":"veggie stix"},"value":96763,"didBreak":false},{"id":"l59XG2","owner":{"id":"VJ5zK","display_name":"jonaTHOT"},"value":97419,"didBreak":false},{"id":"ezRGoM","owner":{"id":"AgJOv","display_name":"uj030221-3551"},"value":97788,"didBreak":false},{"id":"EO9Prx","owner":{"id":"nRJR7","display_name":"Mizuhana"},"value":99976,"didBreak":false},{"id":"45ZzGK","owner":{"id":"nZBPe","display_name":"HiCanIKillYou"},"value":100605,"didBreak":false},{"id":"dazNwK","owner":{"id":"gXXXO","display_name":"\u272a tom1911"},"value":102136,"didBreak":false},{"id":"5GdOpx","owner":{"id":"b7oO6","display_name":"Rico The Saboteur"},"value":102775,"didBreak":false},{"id":"qYWxBo","owner":{"id":"OBwWJ","display_name":"GeGe"},"value":103115,"didBreak":false},{"id":"k2mrmp","owner":{"id":"bxEPx","display_name":"Azean"},"value":103558,"didBreak":false},{"id":"ez2poa","owner":{"id":"AaoBM","display_name":"Linuxx\ue066"},"value":103824,"didBreak":false},{"id":"daayWq","owner":{"id":"nQML4","display_name":"Honn"},"value":104133,"didBreak":false},{"id":"x3jXzO","owner":{"id":"A5lL4","display_name":"Geert wilders"},"value":104393,"didBreak":false},{"id":"QmgXqY","owner":{"id":"AMk3N","display_name":"lionale29ten"},"value":104758,"didBreak":false},{"id":"rdJlNL","owner":{"id":"A5jgd","display_name":"castigo"},"value":104854,"didBreak":false},{"id":"B1gMzm","owner":{"id":"AaKBO","display_name":"BronBerry"},"value":105229,"didBreak":false},{"id":"M58yEN","owner":{"id":"RRmE2","display_name":"piccolo_SPA"},"value":105590,"didBreak":false},{"id":"grYeKE","owner":{"id":"V6wmJ","display_name":"Fabi\u2b50\ufe0fCst"},"value":105846,"didBreak":false},{"id":"3WaNJD","owner":{"id":"VJ5OW","display_name":"BaconPancakes"},"value":105932,"didBreak":false},{"id":"qYNdzX","owner":{"id":"ArwmL","display_name":"Freedom_IT"},"value":106000,"didBreak":false},{"id":"RM7z9Q","owner":{"id":"b8LXR","display_name":"celesteal"},"value":106005,"didBreak":false},{"id":"7lXz43","owner":{"id":"nLRN9","display_name":"Fockey15"},"value":106011,"didBreak":false},{"id":"2Z7gJw","owner":{"id":"b3NwR","display_name":"hopstalgic"},"value":106343,"didBreak":false},{"id":"mKY8WW","owner":{"id":"A59w7","display_name":"aBacIdEe"},"value":106493,"didBreak":false},{"id":"2ZQ8Nk","owner":{"id":"Aowaq","display_name":"Thoomor"},"value":106732,"didBreak":false},{"id":"oq6zO3","owner":{"id":"bNPZo","display_name":"Big Dick Brian"},"value":106747,"didBreak":false},{"id":"6B3Waj","owner":{"id":"p2rj1","display_name":"Strawman"},"value":107073,"didBreak":false},{"id":"pQNrlw","owner":{"id":"bqG1P","display_name":"Jujublackmagic"},"value":107271,"didBreak":false},{"id":"wMa9lz","owner":{"id":"Vw5QR","display_name":"marciochb"},"value":107273,"didBreak":false},{"id":"9Zwqrx","owner":{"id":"V6QoJ","display_name":"tomka700"},"value":107467,"didBreak":false},{"id":"daM5or","owner":{"id":"5QLzZ","display_name":"arvin900"},"value":107622,"didBreak":false},{"id":"ZLweWe","owner":{"id":"AGR7w","display_name":"Bubi"},"value":107914,"didBreak":false},{"id":"RMx9r7","owner":{"id":"nRawr","display_name":"AkillezII"},"value":107922,"didBreak":false},{"id":"ZLK8Ky","owner":{"id":"e37m9","display_name":"Teywer"},"value":108048,"didBreak":false},{"id":"EOYzWo","owner":{"id":"Y44Pl","display_name":"Realyum"},"value":108500,"didBreak":false},{"id":"grrrgM","owner":{"id":"AaDNX","display_name":"Go Seigen"},"value":108578,"didBreak":false},{"id":"8zdkvw","owner":{"id":"1qPza","display_name":"MBS4444"},"value":108825,"didBreak":false},{"id":"RMa58O","owner":{"id":"bm9Pm","display_name":"SmileyFace799"},"value":108900,"didBreak":false},{"id":"daMq17","owner":{"id":"yX9za","display_name":"Kuato"},"value":109241,"didBreak":false},{"id":"QmDDgL","owner":{"id":"bmvMP","display_name":"Shadow Blades"},"value":109264,"didBreak":false},{"id":"5GPEYO","owner":{"id":"AMrq9","display_name":"Jormungandr"},"value":109289,"didBreak":false},{"id":"qY6Qe4","owner":{"id":"nR4vy","display_name":"Beefshankz"},"value":109295,"didBreak":false},{"id":"6BWZZ9","owner":{"id":"bOgdW","display_name":"liquor snurf"},"value":109345,"didBreak":false},{"id":"Qm63lv","owner":{"id":"VlqWL","display_name":"Skriban"},"value":109460,"didBreak":false},{"id":"0ZKXrM","owner":{"id":"b712w","display_name":"schwiftyking"},"value":109468,"didBreak":false},{"id":"ylg0pR","owner":{"id":"yXBGa","display_name":"wumengyundf"},"value":109474,"didBreak":false},{"id":"KvxQxL","owner":{"id":"VzP4D","display_name":"Frits"},"value":109514,"didBreak":false},{"id":"daWwm4","owner":{"id":"b8x6O","display_name":"233333"},"value":109516,"didBreak":false},{"id":"rd65RL","owner":{"id":"VwGgy","display_name":"cam"},"value":109569,"didBreak":false},{"id":"DDxMqy","owner":{"id":"VJ4X7","display_name":"minecat"},"value":109719,"didBreak":false},{"id":"ezaXjE","owner":{"id":"nLdwR","display_name":"chrisrothenhoefer"},"value":109834,"didBreak":false},{"id":"GDvOvR","owner":{"id":"Arrk3","display_name":"davidloh"},"value":109853,"didBreak":false},{"id":"JGoxED","owner":{"id":"A0Gze","display_name":"Bot Zket"},"value":109908,"didBreak":false},{"id":"zJ2GgM","owner":{"id":"p2MBw","display_name":"Jakke"},"value":109995,"didBreak":false},{"id":"v8zr15","owner":{"id":"bxPL7","display_name":"KiQui"},"value":110006,"didBreak":false},{"id":"a5REZO","owner":{"id":"Z3W4d","display_name":"zhaohuaye54"},"value":110061,"didBreak":false},{"id":"GDBEKm","owner":{"id":"VJk8J","display_name":"TTV\/fingeon27"},"value":110121,"didBreak":false},{"id":"wMy10o","owner":{"id":"Pg2Dk","display_name":"Craze"},"value":110152,"didBreak":false},{"id":"5GeyNZ","owner":{"id":"9dwLJ","display_name":"Kalorienreduziert"},"value":110209,"didBreak":false},{"id":"8zxaPm","owner":{"id":"nXM0Q","display_name":"hakejb1"},"value":110219,"didBreak":false},{"id":"GDBXO9","owner":{"id":"nQ6Be","display_name":"I Like Ugly Mammals."},"value":110228,"didBreak":false},{"id":"gr06Ev","owner":{"id":"vMlrD","display_name":"cornshitfuck"},"value":110238,"didBreak":false},{"id":"9ZmDay","owner":{"id":"VPrKw","display_name":"nhaven14"},"value":110239,"didBreak":false},{"id":"1WGO3P","owner":{"id":"V6v2a","display_name":"TobyDog"},"value":110311,"didBreak":false},{"id":"3W6gBD","owner":{"id":"JDMOK","display_name":"tokki10"},"value":110315,"didBreak":false},{"id":"GDBoy6","owner":{"id":"AaKZB","display_name":"Zoom"},"value":110331,"didBreak":false},{"id":"k219B4","owner":{"id":"nXWw7","display_name":"Diggsey"},"value":110331,"didBreak":false},{"id":"RMmdl8","owner":{"id":"bd2PR","display_name":"gundu_001"},"value":110332,"didBreak":false},{"id":"5GeNEZ","owner":{"id":"AWRGk","display_name":"\u6ed1\u5730\u4e0a\u4e4b\u5c0f\u7a3d"},"value":110340,"didBreak":false},{"id":"grBmwM","owner":{"id":"nXd2E","display_name":"Kubu\u015b :*"},"value":110411,"didBreak":false},{"id":"45OoPM","owner":{"id":"nRQXy","display_name":"zerd"},"value":110455,"didBreak":false},{"id":"v86L95","owner":{"id":"nZqEl","display_name":"thueman"},"value":110456,"didBreak":false},{"id":"3WJBeD","owner":{"id":"nRlNe","display_name":"iRevErse Cs"},"value":110496,"didBreak":false},{"id":"zJRke3","owner":{"id":"b8EaP","display_name":"Peppsy"},"value":110498,"didBreak":false},{"id":"KvyGQL","owner":{"id":"a7N6a","display_name":"Bem"},"value":110516,"didBreak":false},{"id":"v8jD0a","owner":{"id":"VPMeX","display_name":"DildoBike"},"value":110517,"didBreak":false},{"id":"5GBKp7","owner":{"id":"bNL9G","display_name":"crocka123"},"value":110537,"didBreak":false},{"id":"k2d1Rp","owner":{"id":"N559o","display_name":"7DimensionalParrot"},"value":110544,"didBreak":false},{"id":"5GaDop","owner":{"id":"VlPW4","display_name":"Stabhole"},"value":110558,"didBreak":false},{"id":"W4K60e","owner":{"id":"ABr6N","display_name":"Thudios"},"value":110595,"didBreak":false},{"id":"8zwDQw","owner":{"id":"mwoE9","display_name":"Mikie"},"value":110603,"didBreak":false},{"id":"Ndga9D","owner":{"id":"AGwPo","display_name":"FrankNirvana"},"value":110611,"didBreak":false},{"id":"oqQWK3","owner":{"id":"e3yez","display_name":"Krazy Koi Fish"},"value":110637,"didBreak":false},{"id":"qYMGeJ","owner":{"id":"Apl69","display_name":"Donald5790"},"value":110653,"didBreak":false},{"id":"l5EEdR","owner":{"id":"2WZgZ","display_name":"Katamari (old)"},"value":110654,"didBreak":false},{"id":"1WGqX0","owner":{"id":"q7MYq","display_name":"jbmisi14"},"value":110656,"didBreak":false},{"id":"JGy7XW","owner":{"id":"bxO05","display_name":"xBrowi"},"value":110658,"didBreak":false},{"id":"W4O6kz","owner":{"id":"b29Kk","display_name":"pineapplebacon777"},"value":110667,"didBreak":false},{"id":"GDRQYw","owner":{"id":"nKBoL","display_name":"Murkaeus"},"value":110684,"didBreak":false},{"id":"Pey6aQ","owner":{"id":"AGkwR","display_name":"theo.louesdon"},"value":110697,"didBreak":false},{"id":"zJ8wjG","owner":{"id":"bdlZ4","display_name":"CkyNik"},"value":110710,"didBreak":false},{"id":"pQ9Yg5","owner":{"id":"p2v1o","display_name":"marcus.wasastjerna"},"value":110747,"didBreak":false},{"id":"a5NyDB","owner":{"id":"9dW8x","display_name":"frotnight funy"},"value":110750,"didBreak":false},{"id":"zJO7B7","owner":{"id":"ABwl7","display_name":"Aklhys"},"value":110758,"didBreak":false},{"id":"OpvQ3a","owner":{"id":"nyJ4N","display_name":"coolninjaboyudude1234"},"value":110763,"didBreak":false},{"id":"RM65ex","owner":{"id":"b72RP","display_name":"Smplstx"},"value":110765,"didBreak":false},{"id":"9Z7Rqr","owner":{"id":"VPQRY","display_name":"R"},"value":110771,"didBreak":false},{"id":"5GZxq4","owner":{"id":"a7Kda","display_name":"Outragedgamer14"},"value":110778,"didBreak":false},{"id":"3W4JE8","owner":{"id":"bd997","display_name":"Marijn"},"value":110787,"didBreak":false},{"id":"PeK4WQ","owner":{"id":"nygK7","display_name":"kristoffer"},"value":110794,"didBreak":false},{"id":"GDB3Wo","owner":{"id":"AogYX","display_name":"Caligula"},"value":110797,"didBreak":false},{"id":"qYjreP","owner":{"id":"b8Jkl","display_name":"Sloane"},"value":110802,"didBreak":false},{"id":"JG8OD7","owner":{"id":"b7w86","display_name":"vkelloku"},"value":110854,"didBreak":false},{"id":"GD8dP9","owner":{"id":"xNJv8","display_name":"Gibby"},"value":110855,"didBreak":false},{"id":"EOvLYP","owner":{"id":"nyMj3","display_name":"Hazmat"},"value":110857,"didBreak":false},{"id":"l5Wm0P","owner":{"id":"Ag9yv","display_name":"DuuSuu"},"value":110859,"didBreak":false},{"id":"RMDaJr","owner":{"id":"AG0zm","display_name":"315Lukas"},"value":110870,"didBreak":false},{"id":"x3jyjP","owner":{"id":"b7BDz","display_name":"Mulalu"},"value":110881,"didBreak":false},{"id":"RMN9x2","owner":{"id":"1q0PK","display_name":"joseph.pesqui"},"value":110890,"didBreak":false},{"id":"k22xjp","owner":{"id":"W7ZMe","display_name":"rainy"},"value":110893,"didBreak":false},{"id":"8zd0gO","owner":{"id":"nXBXz","display_name":"lazy comet"},"value":110898,"didBreak":false},{"id":"PeMNal","owner":{"id":"vMpo9","display_name":"Maistas"},"value":110900,"didBreak":false},{"id":"RMD83j","owner":{"id":"K8eN0","display_name":"-1-1-"},"value":110900,"didBreak":false},{"id":"zJzLLo","owner":{"id":"AGRgD","display_name":"Bull Moose"},"value":110908,"didBreak":false},{"id":"dazlEG","owner":{"id":"AaJLl","display_name":"palfly15"},"value":110925,"didBreak":false},{"id":"daKzv4","owner":{"id":"bmW4E","display_name":"pome.\ud83d\ude08"},"value":110932,"didBreak":false},{"id":"JG44ZJ","owner":{"id":"bN7JG","display_name":"AZ-LT"},"value":110939,"didBreak":false},{"id":"OpQx2R","owner":{"id":"n90yJ","display_name":"Aviven11"},"value":110939,"didBreak":false},{"id":"pQ1LY8","owner":{"id":"q72do","display_name":"True SmolSir"},"value":110946,"didBreak":false},{"id":"daoELd","owner":{"id":"VlMk3","display_name":"RisingStar"},"value":110950,"didBreak":false},{"id":"qY7yGJ","owner":{"id":"b1QmX","display_name":"chenail.liam"},"value":110957,"didBreak":false},{"id":"7lWBqR","owner":{"id":"b8Z7l","display_name":"Fiku121"},"value":110964,"didBreak":false},{"id":"PejwQl","owner":{"id":"b21WG","display_name":"Hyppis"},"value":110983,"didBreak":false},{"id":"9Z0w2x","owner":{"id":"b1EWK","display_name":"lukas.bornheim"},"value":110986,"didBreak":false},{"id":"8zgEra","owner":{"id":"bjk4J","display_name":"duvald16"},"value":110988,"didBreak":false},{"id":"pQRDzR","owner":{"id":"nRgg7","display_name":"XxTrollFacexX"},"value":110989,"didBreak":false},{"id":"v8k9Op","owner":{"id":"AWwNk","display_name":"iwantmore29"},"value":110991,"didBreak":false},{"id":"l51E3R","owner":{"id":"nQ4Rv","display_name":"razpe"},"value":110994,"didBreak":false},{"id":"ezM4oa","owner":{"id":"nZQrd","display_name":"plush"},"value":110996,"didBreak":false},{"id":"wM110y","owner":{"id":"bdPo4","display_name":"smokedscrod"},"value":110997,"didBreak":false},{"id":"qYNJKq","owner":{"id":"A5JLg","display_name":"gijshomminga7"},"value":110997,"didBreak":false},{"id":"M5lPKM","owner":{"id":"q7e4o","display_name":"Uniquepotatoes"},"value":110998,"didBreak":false},{"id":"NdLwdv","owner":{"id":"K81qp","display_name":"TucLTU"},"value":110998,"didBreak":false},{"id":"5G3ykx","owner":{"id":"bdXQq","display_name":"Starstorm"},"value":110998,"didBreak":false},{"id":"a5NzkX","owner":{"id":"Aa2El","display_name":"Matty90509"},"value":110999,"didBreak":false},{"id":"XZaa4Z","owner":{"id":"bOoQB","display_name":"Bushy"},"value":111000,"didBreak":false},{"id":"B12r4d","owner":{"id":"bODpX","display_name":"Groovemouse"},"value":111000,"didBreak":false},{"id":"RMv7g9","owner":{"id":"b1vyY","display_name":"zezetel"},"value":111000,"didBreak":false},{"id":"ZLargO","owner":{"id":"Vz87D","display_name":"Kastrull"},"value":111000,"didBreak":false},{"id":"l594m3","owner":{"id":"QOmOe","display_name":"arronon"},"value":111000,"didBreak":false},{"id":"PeNyql","owner":{"id":"AaqKe","display_name":"Pugloney29"},"value":111000,"didBreak":false},{"id":"LaEe9l","owner":{"id":"a7OjO","display_name":"tetsu_yamamon"},"value":111000,"didBreak":false},{"id":"OpNqkm","owner":{"id":"EBzP2","display_name":"lollyH2O"},"value":113929,"didBreak":false},{"id":"qY6Zo4","owner":{"id":"ArX03","display_name":"FusedZirconium"},"value":115907,"didBreak":false},{"id":"ezyWwa","owner":{"id":"b3Gq3","display_name":"colinblue57"},"value":130526,"didBreak":false},{"id":"8zdzQL","owner":{"id":"AG29x","display_name":"Frit\u00f6senfett Fred"},"value":157218,"didBreak":false},{"id":"qYZKPL","owner":{"id":"Arv0Q","display_name":"Navet"},"value":160622,"didBreak":false},{"id":"jeozkR","owner":{"id":"b2Y9a","display_name":"Terra_Pringles"},"value":215125,"didBreak":false}],"metadata":{"uniqueRanksCount":176}}}